Workbook
Name Slicer_Month_Name: #N/A
Name Slicer_Sales_Channel: #N/A

Sheet Raw Data
A1: Order ID | B1: Order Date | C1: Order Time | D1: Customer Name | E1: Email | F1: Phone | G1: City | H1: State | I1: Country | J1: Line Items | K1: Primary Category | L1: Total Items | M1: Subtotal ($) | N1: Discount Code | O1: Discount Amount ($) | P1: Shipping ($) | Q1: Tax ($) | R1: Order Total ($) | S1: Payment Method | T1: Sales Channel | U1: Fulfillment Status | V1: Fulfillment Date | W1: Refund Amount ($)
A2: #ORD-10001 | B2: 2024-02-24 | C2: 04:35:15 | D2: Mason Johnson | E2: mason.johnson36@gmail.com | F2: +1-933-765-9928 | G2: Portland | H2: OR | I2: United States | J2: Anti-Aging Serum 1oz x1 | Men's Grooming Kit x1 | Leather Wallet Slim x1 | K2: Beauty | L2: 3 | M2: 115.97 | N2: None | O2: 0 | P2: 0 | Q2: 8.12 | R2: 124.09 | S2: Credit Card | T2: Facebook | U2: Refunded | V2: 2024-02-26 | W2: 124.09
A3: #ORD-10002 | B3: 2024-12-03 | C3: 14:27:58 | D3: Sofia Anderson | E3: sofia.anderson76@gmail.com | F3: +1-294-489-2584 | G3: Charlotte | H3: NC | I3: United States | J3: High-Waist Leggings x1 | K3: Apparel | L3: 1 | M3: 42.99 | N3: WELCOME15 | O3: 6.45 | P3: 7.99 | Q3: 2.92 | R3: 47.45 | S3: Credit Card | T3: TikTok Shop | U3: Partially Fulfilled | V3: 2024-12-04 | W3: 0
A4: #ORD-10003 | B4: 2024-07-27 | C4: 06:00:29 | D4: Emily Thompson | E4: emily.thompson34@outlook.com | F4: +1-246-777-4733 | G4: Nashville | H4: TN | I4: United States | J4: Bamboo Sunglasses x1 | K4: Bags & Accessories | L4: 1 | M4: 24.99 | N4: FLASH25 | O4: 6.25 | P4: 7.99 | Q4: 1.87 | R4: 28.6 | S4: PayPal | T4: Direct | U4: Fulfilled | V4: 2024-07-28 | W4: 0
A5: #ORD-10004 | B5: 2024-06-25 | C5: 02:05:25 | D5: Evelyn Garcia | E5: evelyn.garcia30@yahoo.com | F5: +1-946-350-3677 | G5: Milwaukee | H5: WI | I5: United States | J5: Insulated Water Bottle 32oz x1 | Running Shoes - Men's x1 | K5: Sports & Fitness | L5: 2 | M5: 102.98 | N5: SAVE10 | O5: 10.3 | P5: 0 | Q5: 9.27 | R5: 101.95 | S5: Google Pay | T5: Facebook | U5: Fulfilled | V5: 2024-06-30 | W5: 0
A6: #ORD-10005 | B6: 2024-05-05 | C6: 22:32:02 | D6: Sebastian Harris | E6: sebastian.harris82@yahoo.com | F6: +1-871-611-7482 | G6: Dallas | H6: TX | I6: United States | J6: Classic Fit Polo Shirt x2 | Portable Bluetooth Speaker x2 | Casual Sneakers x1 | K6: Apparel | L6: 3 | M6: 229.95 | N6: None | O6: 0 | P6: 0 | Q6: 16.1 | R6: 246.05 | S6: Google Pay | T6: Facebook | U6: Partially Fulfilled | V6: 2024-05-07 | W6: 0
A7: #ORD-10006 | B7: 2024-08-06 | C7: 00:19:48 | D7: Sebastian Martinez | E7: sebastian.martinez18@gmail.com | F7: +1-293-873-1771 | G7: Dallas | H7: TX | I7: United States | J7: Men's Grooming Kit x1 | Linen Throw Blanket x1 | K7: Beauty | L7: 2 | M7: 75.98 | N7: SAVE10 | O7: 7.6 | P7: 0 | Q7: 4.79 | R7: 73.17 | S7: Afterpay | T7: Online Store | U7: Cancelled | W7: 0
A8: #ORD-10007 | B8: 2024-01-25 | C8: 16:07:16 | D8: Mason Martinez | E8: mason.martinez21@yahoo.com | F8: +1-968-373-6573 | G8: Oklahoma City | H8: OK | I8: United States | J8: Scented Soy Candle Set x3 | K8: Home & Living | L8: 1 | M8: 68.97 | N8: FLASH25 | O8: 17.24 | P8: 7.99 | Q8: 4.66 | R8: 64.38 | S8: Apple Pay | T8: Online Store | U8: Fulfilled | V8: 2024-01-30 | W8: 0
A9: #ORD-10008 | B9: 2024-10-07 | C9: 10:23:08 | D9: Mason Jackson | E9: mason.jackson21@gmail.com | F9: +1-752-897-9689 | G9: Columbus | H9: OH | I9: United States | J9: Hiking Boots x1 | Air Fryer 5.8Qt x2 | Classic Fit Polo Shirt x2 | K9: Footwear | L9: 3 | M9: 339.95 | N9: SAVE10 | O9: 33.99 | P9: 0 | Q9: 30.6 | R9: 336.56 | S9: Debit Card | T9: Online Store | U9: Partially Fulfilled | V9: 2024-10-09 | W9: 0
A10: #ORD-10009 | B10: 2024-12-26 | C10: 19:49:36 | D10: Emma Flores | E10: emma.flores63@gmail.com | F10: +1-949-597-2133 | G10: Austin | H10: TX | I10: United States | J10: Denim Jacket x2 | K10: Apparel | L10: 1 | M10: 129.98 | N10: None | O10: 0 | P10: 0 | Q10: 7.8 | R10: 137.78 | S10: Credit Card | T10: Facebook | U10: Fulfilled | V10: 2024-12-27 | W10: 0
A11: #ORD-10010 | B11: 2024-08-01 | C11: 12:32:27 | D11: Grace Rodriguez | E11: grace.rodriguez85@gmail.com | F11: +1-608-787-7118 | G11: Phoenix | H11: AZ | I11: United States | J11: Air Fryer 5.8Qt x2 | K11: Kitchen | L11: 1 | M11: 159.98 | N11: WELCOME15 | O11: 24 | P11: 0 | Q11: 9.52 | R11: 145.5 | S11: Google Pay | T11: Google Shopping | U11: Fulfilled | V11: 2024-08-04 | W11: 0
A12: #ORD-10011 | B12: 2024-01-25 | C12: 20:45:52 | D12: Avery Wright | E12: avery.wright16@gmail.com | F12: +1-232-980-6413 | G12: Charlotte | H12: NC | I12: United States | J12: Linen Throw Blanket x1 | K12: Home & Living | L12: 1 | M12: 39.99 | N12: LOYALTY5 | O12: 2 | P12: 5.99 | Q12: 2.28 | R12: 46.26 | S12: Credit Card | T12: Facebook | U12: Fulfilled | V12: 2024-01-26 | W12: 0
A13: #ORD-10012 | B13: 2024-02-21 | C13: 09:14:08 | D13: Ava King | E13: ava.king36@yahoo.com | F13: +1-620-578-1887 | G13: San Diego | H13: CA | I13: United States | J13: Leather Wallet Slim x1 | Linen Throw Blanket x1 | K13: Bags & Accessories | L13: 2 | M13: 69.98 | N13: SUMMER20 | O13: 14 | P13: 9.99 | Q13: 3.92 | R13: 69.89 | S13: Credit Card | T13: Facebook | U13: Partially Fulfilled | V13: 2024-02-25 | W13: 0
A14: #ORD-10013 | B14: 2024-11-30 | C14: 15:22:12 | D14: Sophia Brown | E14: sophia.brown94@gmail.com | F14: +1-763-200-1828 | G14: Fort Worth | H14: TX | I14: United States | J14: Running Shoes - Women's x1 | K14: Footwear | L14: 1 | M14: 69.99 | N14: SUMMER20 | O14: 14 | P14: 5.99 | Q14: 4.76 | R14: 66.74 | S14: Credit Card | T14: Instagram | U14: Fulfilled | V14: 2024-12-04 | W14: 0
A15: #ORD-10014 | B15: 2024-07-07 | C15: 14:30:12 | D15: Grace Smith | E15: grace.smith97@yahoo.com | F15: +1-492-533-8973 | G15: Chicago | H15: IL | I15: United States | J15: Canvas Backpack 25L x2 | Protein Powder Chocolate 2lb x1 | K15: Bags & Accessories | L15: 2 | M15: 154.97 | N15: None | O15: 0 | P15: 0 | Q15: 13.17 | R15: 168.14 | S15: Credit Card | T15: Email Campaign | U15: Cancelled | W15: 0
A16: #ORD-10015 | B16: 2024-07-29 | C16: 13:37:32 | D16: James Gonzalez | E16: james.gonzalez28@outlook.com | F16: +1-282-971-4044 | G16: San Jose | H16: CA | I16: United States | J16: Resistance Band Set x1 | K16: Sports & Fitness | L16: 1 | M16: 24.99 | N16: LOYALTY5 | O16: 1.25 | P16: 9.99 | Q16: 2.14 | R16: 35.87 | S16: Google Pay | T16: Instagram | U16: Fulfilled | V16: 2024-08-03 | W16: 0
A17: #ORD-10016 | B17: 2024-12-31 | C17: 16:18:43 | D17: Ava Flores | E17: ava.flores87@yahoo.com | F17: +1-334-787-5915 | G17: Chicago | H17: IL | I17: United States | J17: Casual Sneakers x1 | Linen Throw Blanket x1 | Scented Soy Candle Set x1 | Portable Bluetooth Speaker x1 | K17: Footwear | L17: 4 | M17: 172.96 | N17: SAVE10 | O17: 17.3 | P17: 0 | Q17: 10.9 | R17: 166.56 | S17: PayPal | T17: Online Store | U17: Fulfilled | V17: 2025-01-04 | W17: 0
A18: #ORD-10017 | B18: 2024-08-29 | C18: 05:37:25 | D18: Sebastian Lee | E18: sebastian.lee97@yahoo.com | F18: +1-883-936-5905 | G18: Tucson | H18: AZ | I18: United States | J18: Smart LED Desk Lamp x1 | USB-C Fast Charger 65W x3 | Coffee Maker Programmable x2 | Running Shoes - Women's x2 | Air Fryer 5.8Qt x1 | K18: Electronics | L18: 5 | M18: 459.91 | N18: None | O18: 0 | P18: 0 | Q18: 39.09 | R18: 499 | S18: Apple Pay | T18: Google Shopping | U18: Refunded | V18: 2024-08-30 | W18: 499
A19: #ORD-10018 | B19: 2024-03-01 | C19: 08:52:46 | D19: Sophia Rodriguez | E19: sophia.rodriguez15@outlook.com | F19: +1-457-966-1832 | G19: Dallas | H19: TX | I19: United States | J19: Scented Soy Candle Set x1 | K19: Home & Living | L19: 1 | M19: 22.99 | N19: SAVE10 | O19: 2.3 | P19: 5.99 | Q19: 2.07 | R19: 28.75 | S19: PayPal | T19: Online Store | U19: Cancelled | W19: 0
A20: #ORD-10019 | B20: 2024-05-09 | C20: 12:58:20 | D20: Ethan Lewis | E20: ethan.lewis36@gmail.com | F20: +1-236-954-7049 | G20: Baltimore | H20: MD | I20: United States | J20: Essential Oil Diffuser x2 | Hiking Boots x1 | Running Shoes - Men's x1 | K20: Home & Living | L20: 3 | M20: 250.96 | N20: None | O20: 0 | P20: 0 | Q20: 15.06 | R20: 266.02 | S20: Credit Card | T20: Direct | U20: Fulfilled | V20: 2024-05-14 | W20: 0
A21: #ORD-10020 | B21: 2024-04-29 | C21: 17:10:33 | D21: Daniel Torres | E21: daniel.torres56@gmail.com | F21: +1-616-735-3532 | G21: Phoenix | H21: AZ | I21: United States | J21: Bamboo Sunglasses x2 | K21: Bags & Accessories | L21: 1 | M21: 49.98 | N21: None | O21: 0 | P21: 7.99 | Q21: 3.5 | R21: 61.47 | S21: PayPal | T21: Facebook | U21: Partially Fulfilled | V21: 2024-05-04 | W21: 0
A22: #ORD-10021 | B22: 2024-10-13 | C22: 01:16:42 | D22: Oliver Hernandez | E22: oliver.hernandez23@yahoo.com | F22: +1-671-458-6000 | G22: Louisville | H22: KY | I22: United States | J22: High-Waist Leggings x2 | Bamboo Sunglasses x2 | Multivitamin Daily Pack x1 | Anti-Aging Serum 1oz x2 | K22: Apparel | L22: 4 | M22: 255.93 | N22: None | O22: 0 | P22: 0 | Q22: 21.75 | R22: 277.68 | S22: Apple Pay | T22: Direct | U22: Fulfilled | V22: 2024-10-15 | W22: 0
A23: #ORD-10022 | B23: 2024-05-07 | C23: 11:37:23 | D23: Amelia Anderson | E23: amelia.anderson85@gmail.com | F23: +1-228-218-5279 | G23: New York | H23: NY | I23: United States | J23: USB-C Fast Charger 65W x3 | K23: Electronics | L23: 1 | M23: 89.97 | N23: SAVE10 | O23: 9 | P23: 0 | Q23: 6.48 | R23: 87.45 | S23: PayPal | T23: Online Store | U23: Refunded | V23: 2024-05-10 | W23: 87.45
A24: #ORD-10023 | B24: 2024-06-17 | C24: 18:25:40 | D24: Logan Hill | E24: logan.hill5@gmail.com | F24: +1-201-632-9821 | G24: Dallas | H24: TX | I24: United States | J24: High-Waist Leggings x1 | K24: Apparel | L24: 1 | M24: 42.99 | N24: LOYALTY5 | O24: 2.15 | P24: 4.99 | Q24: 3.47 | R24: 49.3 | S24: Apple Pay | T24: Online Store | U24: Fulfilled | V24: 2024-06-21 | W24: 0
A25: #ORD-10024 | B25: 2024-08-30 | C25: 00:13:45 | D25: Charlotte White | E25: charlotte.white9@outlook.com | F25: +1-330-296-7888 | G25: Columbus | H25: OH | I25: United States | J25: Canvas Backpack 25L x1 | K25: Bags & Accessories | L25: 1 | M25: 54.99 | N25: SAVE10 | O25: 5.5 | P25: 7.99 | Q25: 4.95 | R25: 62.43 | S25: Debit Card | T25: Instagram | U25: Fulfilled | V25: 2024-09-04 | W25: 0
A26: #ORD-10025 | B26: 2024-07-31 | C26: 19:08:41 | D26: Elizabeth Lopez | E26: elizabeth.lopez73@gmail.com | F26: +1-490-627-6491 | G26: Nashville | H26: TN | I26: United States | J26: Yoga Mat Premium x2 | Running Shoes - Women's x1 | Multivitamin Daily Pack x1 | K26: Sports & Fitness | L26: 3 | M26: 159.96 | N26: SUMMER20 | O26: 31.99 | P26: 0 | Q26: 10.88 | R26: 138.85 | S26: PayPal | T26: Instagram | U26: Fulfilled | V26: 2024-08-01 | W26: 0
A27: #ORD-10026 | B27: 2024-03-18 | C27: 08:01:31 | D27: Ethan Thomas | E27: ethan.thomas40@gmail.com | F27: +1-706-509-4997 | G27: El Paso | H27: TX | I27: United States | J27: Portable Bluetooth Speaker x1 | K27: Electronics | L27: 1 | M27: 49.99 | N27: SUMMER20 | O27: 10 | P27: 4.99 | Q27: 3.4 | R27: 48.38 | S27: Debit Card | T27: Facebook | U27: Fulfilled | V27: 2024-03-22 | W27: 0
A28: #ORD-10027 | B28: 2024-10-29 | C28: 07:24:14 | D28: James Smith | E28: james.smith97@outlook.com | F28: +1-336-920-8612 | G28: Albuquerque | H28: NM | I28: United States | J28: Running Shoes - Men's x2 | K28: Footwear | L28: 1 | M28: 149.98 | N28: FLASH25 | O28: 37.49 | P28: 0 | Q28: 9.56 | R28: 122.05 | S28: Credit Card | T28: Online Store | U28: Fulfilled | V28: 2024-11-02 | W28: 0
A29: #ORD-10028 | B29: 2024-08-25 | C29: 22:20:00 | D29: Owen Torres | E29: owen.torres41@outlook.com | F29: +1-696-741-4919 | G29: Nashville | H29: TN | I29: United States | J29: Leather Wallet Slim x2 | Air Fryer 5.8Qt x1 | Multivitamin Daily Pack x2 | K29: Bags & Accessories | L29: 3 | M29: 179.95 | N29: SUMMER20 | O29: 35.99 | P29: 0 | Q29: 12.24 | R29: 156.2 | S29: Credit Card | T29: Online Store | U29: Fulfilled | V29: 2024-08-30 | W29: 0
A30: #ORD-10029 | B30: 2024-04-15 | C30: 12:34:06 | D30: Elijah Robinson | E30: elijah.robinson92@gmail.com | F30: +1-624-517-6421 | G30: Chicago | H30: IL | I30: United States | J30: Leather Wallet Slim x1 | K30: Bags & Accessories | L30: 1 | M30: 29.99 | N30: None | O30: 0 | P30: 5.99 | Q30: 2.1 | R30: 38.08 | S30: Debit Card | T30: Online Store | U30: Fulfilled | V30: 2024-04-16 | W30: 0
A31: #ORD-10030 | B31: 2024-06-12 | C31: 04:01:17 | D31: Grace Walker | E31: grace.walker8@gmail.com | F31: +1-629-651-9947 | G31: Columbus | H31: OH | I31: United States | J31: Classic Fit Polo Shirt x1 | K31: Apparel | L31: 1 | M31: 34.99 | N31: None | O31: 0 | P31: 9.99 | Q31: 2.97 | R31: 47.95 | S31: Credit Card | T31: Online Store | U31: Unfulfilled | W31: 0
A32: #ORD-10031 | B32: 2024-07-07 | C32: 14:30:41 | D32: Victoria Anderson | E32: victoria.anderson29@gmail.com | F32: +1-603-706-1444 | G32: Indianapolis | H32: IN | I32: United States | J32: Resistance Band Set x1 | K32: Sports & Fitness | L32: 1 | M32: 24.99 | N32: WELCOME15 | O32: 3.75 | P32: 5.99 | Q32: 1.81 | R32: 29.04 | S32: Google Pay | T32: Referral | U32: Refunded | V32: 2024-07-08 | W32: 29.04
A33: #ORD-10032 | B33: 2024-04-11 | C33: 00:49:57 | D33: Ethan Lewis | E33: ethan.lewis60@gmail.com | F33: +1-681-119-9837 | G33: Phoenix | H33: AZ | I33: United States | J33: Running Shoes - Women's x1 | K33: Footwear | L33: 1 | M33: 69.99 | N33: SAVE10 | O33: 7 | P33: 9.99 | Q33: 5.04 | R33: 78.02 | S33: Shop Pay | T33: Email Campaign | U33: Fulfilled | V33: 2024-04-12 | W33: 0
A34: #ORD-10033 | B34: 2024-09-10 | C34: 02:47:37 | D34: Noah Thompson | E34: noah.thompson84@gmail.com | F34: +1-885-217-4571 | G34: San Diego | H34: CA | I34: United States | J34: Wireless Noise-Cancelling Headphones x3 | K34: Electronics | L34: 1 | M34: 269.97 | N34: None | O34: 0 | P34: 0 | Q34: 16.2 | R34: 286.17 | S34: PayPal | T34: Online Store | U34: Cancelled | W34: 0
A35: #ORD-10034 | B35: 2024-08-23 | C35: 19:57:24 | D35: Sebastian Taylor | E35: sebastian.taylor48@gmail.com | F35: +1-913-891-5941 | G35: Memphis | H35: TN | I35: United States | J35: Sunscreen SPF 50 Face x3 | Smart LED Desk Lamp x1 | Classic Fit Polo Shirt x1 | Denim Jacket x1 | Running Shoes - Men's x1 | K35: Beauty | L35: 5 | M35: 271.93 | N35: WELCOME15 | O35: 40.79 | P35: 0 | Q35: 19.65 | R35: 250.79 | S35: Google Pay | T35: Online Store | U35: Fulfilled | V35: 2024-08-24 | W35: 0
A36: #ORD-10035 | B36: 2024-06-15 | C36: 08:46:20 | D36: Victoria Davis | E36: victoria.davis73@yahoo.com | F36: +1-924-256-8135 | G36: Louisville | H36: KY | I36: United States | J36: USB-C Fast Charger 65W x1 | Air Fryer 5.8Qt x1 | K36: Electronics | L36: 2 | M36: 109.98 | N36: WELCOME15 | O36: 16.5 | P36: 0 | Q36: 7.95 | R36: 101.43 | S36: Credit Card | T36: TikTok Shop | U36: Cancelled | W36: 0
A37: #ORD-10036 | B37: 2024-10-27 | C37: 20:10:53 | D37: Logan Wright | E37: logan.wright35@outlook.com | F37: +1-783-724-7209 | G37: Oklahoma City | H37: OK | I37: United States | J37: Multivitamin Daily Pack x2 | Denim Jacket x1 | K37: Health & Nutrition | L37: 2 | M37: 104.97 | N37: None | O37: 0 | P37: 0 | Q37: 6.3 | R37: 111.27 | S37: Credit Card | T37: Instagram | U37: Cancelled | W37: 0
A38: #ORD-10037 | B38: 2024-03-23 | C38: 09:06:01 | D38: Muhammad Johnson | E38: muhammad.johnson42@gmail.com | F38: +1-287-347-7658 | G38: Indianapolis | H38: IN | I38: United States | J38: Hiking Boots x1 | K38: Footwear | L38: 1 | M38: 109.99 | N38: LOYALTY5 | O38: 5.5 | P38: 0 | Q38: 10.45 | R38: 114.94 | S38: Apple Pay | T38: Facebook | U38: Refunded | V38: 2024-03-25 | W38: 114.94
A39: #ORD-10038 | B39: 2024-07-09 | C39: 14:47:11 | D39: Michael Torres | E39: michael.torres31@outlook.com | F39: +1-766-643-6632 | G39: Memphis | H39: TN | I39: United States | J39: Wireless Noise-Cancelling Headphones x1 | K39: Electronics | L39: 1 | M39: 89.99 | N39: None | O39: 0 | P39: 0 | Q39: 7.65 | R39: 97.64 | S39: PayPal | T39: Online Store | U39: Partially Fulfilled | V39: 2024-07-13 | W39: 0
A40: #ORD-10039 | B40: 2024-04-07 | C40: 15:15:07 | D40: Jack Torres | E40: jack.torres46@yahoo.com | F40: +1-489-202-4180 | G40: Austin | H40: TX | I40: United States | J40: Men's Grooming Kit x1 | K40: Beauty | L40: 1 | M40: 35.99 | N40: None | O40: 0 | P40: 5.99 | Q40: 2.52 | R40: 44.5 | S40: Credit Card | T40: Instagram | U40: Refunded | V40: 2024-04-12 | W40: 44.5
A41: #ORD-10040 | B41: 2024-10-01 | C41: 23:12:38 | D41: Evelyn Anderson | E41: evelyn.anderson23@gmail.com | F41: +1-491-580-8843 | G41: Jacksonville | H41: FL | I41: United States | J41: Hiking Boots x3 | Portable Bluetooth Speaker x1 | K41: Footwear | L41: 2 | M41: 379.96 | N41: None | O41: 0 | P41: 0 | Q41: 38 | R41: 417.96 | S41: Apple Pay | T41: Instagram | U41: Fulfilled | V41: 2024-10-06 | W41: 0
A42: #ORD-10041 | B42: 2024-11-30 | C42: 15:50:24 | D42: Avery Perez | E42: avery.perez7@gmail.com | F42: +1-454-221-7818 | G42: Philadelphia | H42: PA | I42: United States | J42: Denim Jacket x1 | USB-C Fast Charger 65W x1 | K42: Apparel | L42: 2 | M42: 94.98 | N42: None | O42: 0 | P42: 0 | Q42: 6.65 | R42: 101.63 | S42: Credit Card | T42: Facebook | U42: Fulfilled | V42: 2024-12-01 | W42: 0
A43: #ORD-10042 | B43: 2024-07-21 | C43: 22:43:44 | D43: Victoria Flores | E43: victoria.flores80@gmail.com | F43: +1-840-316-5335 | G43: Louisville | H43: KY | I43: United States | J43: Bamboo Sunglasses x1 | K43: Bags & Accessories | L43: 1 | M43: 24.99 | N43: LOYALTY5 | O43: 1.25 | P43: 9.99 | Q43: 1.9 | R43: 35.63 | S43: PayPal | T43: Online Store | U43: Fulfilled | V43: 2024-07-23 | W43: 0
A44: #ORD-10043 | B44: 2024-06-07 | C44: 15:39:35 | D44: Ethan Hernandez | E44: ethan.hernandez23@yahoo.com | F44: +1-840-703-4241 | G44: San Diego | H44: CA | I44: United States | J44: Scented Soy Candle Set x1 | Stainless Steel Cookware Set x1 | K44: Home & Living | L44: 2 | M44: 152.98 | N44: SAVE10 | O44: 15.3 | P44: 0 | Q44: 13.77 | R44: 151.45 | S44: Apple Pay | T44: Online Store | U44: Fulfilled | V44: 2024-06-10 | W44: 0
A45: #ORD-10044 | B45: 2024-11-17 | C45: 00:45:39 | D45: Jack Davis | E45: jack.davis29@outlook.com | F45: +1-478-612-9847 | G45: Seattle | H45: WA | I45: United States | J45: Portable Bluetooth Speaker x1 | K45: Electronics | L45: 1 | M45: 49.99 | N45: SAVE10 | O45: 5 | P45: 7.99 | Q45: 3.82 | R45: 56.8 | S45: Credit Card | T45: Google Shopping | U45: Unfulfilled | W45: 0
A46: #ORD-10045 | B46: 2024-06-16 | C46: 18:47:56 | D46: Michael Robinson | E46: michael.robinson77@gmail.com | F46: +1-241-881-3870 | G46: Chicago | H46: IL | I46: United States | J46: Scented Soy Candle Set x1 | Hiking Boots x3 | Wireless Noise-Cancelling Headphones x2 | K46: Home & Living | L46: 3 | M46: 532.94 | N46: LOYALTY5 | O46: 26.65 | P46: 0 | Q46: 45.57 | R46: 551.86 | S46: Klarna | T46: Referral | U46: Fulfilled | V46: 2024-06-21 | W46: 0
A47: #ORD-10046 | B47: 2024-08-15 | C47: 07:40:03 | D47: Ella Wright | E47: ella.wright57@yahoo.com | F47: +1-537-521-9117 | G47: Oklahoma City | H47: OK | I47: United States | J47: Denim Jacket x1 | K47: Apparel | L47: 1 | M47: 64.99 | N47: None | O47: 0 | P47: 9.99 | Q47: 5.2 | R47: 80.18 | S47: Debit Card | T47: Online Store | U47: Fulfilled | V47: 2024-08-17 | W47: 0
A48: #ORD-10047 | B48: 2024-05-02 | C48: 03:30:44 | D48: Evelyn Sanchez | E48: evelyn.sanchez98@yahoo.com | F48: +1-623-155-4073 | G48: Baltimore | H48: MD | I48: United States | J48: Smart LED Desk Lamp x3 | K48: Electronics | L48: 1 | M48: 119.97 | N48: WELCOME15 | O48: 18 | P48: 0 | Q48: 9.18 | R48: 111.15 | S48: Shop Pay | T48: Online Store | U48: Refunded | V48: 2024-05-06 | W48: 111.15
A49: #ORD-10048 | B49: 2024-06-20 | C49: 16:07:13 | D49: Owen White | E49: owen.white97@gmail.com | F49: +1-518-664-1224 | G49: Nashville | H49: TN | I49: United States | J49: Running Shoes - Women's x1 | Hiking Boots x1 | Coffee Maker Programmable x2 | K49: Footwear | L49: 3 | M49: 289.96 | N49: SUMMER20 | O49: 57.99 | P49: 0 | Q49: 13.92 | R49: 245.89 | S49: Credit Card | T49: Facebook | U49: Fulfilled | V49: 2024-06-22 | W49: 0
A50: #ORD-10049 | B50: 2024-06-28 | C50: 05:00:21 | D50: William Clark | E50: william.clark29@outlook.com | F50: +1-395-713-9327 | G50: Chicago | H50: IL | I50: United States | J50: Essential Oil Diffuser x3 | Denim Jacket x1 | Mechanical Keyboard x2 | Stainless Steel Cookware Set x1 | K50: Home & Living | L50: 4 | M50: 533.93 | N50: SUMMER20 | O50: 106.79 | P50: 0 | Q50: 36.31 | R50: 463.45 | S50: Credit Card | T50: Facebook | U50: Unfulfilled | W50: 0
A51: #ORD-10050 | B51: 2024-12-28 | C51: 19:49:34 | D51: Isabella Jones | E51: isabella.jones99@yahoo.com | F51: +1-981-656-7180 | G51: Dallas | H51: TX | I51: United States | J51: Hiking Boots x1 | Denim Jacket x1 | Wireless Noise-Cancelling Headphones x1 | K51: Footwear | L51: 3 | M51: 264.97 | N51: SUMMER20 | O51: 52.99 | P51: 0 | Q51: 14.84 | R51: 226.82 | S51: Debit Card | T51: Instagram | U51: Partially Fulfilled | V51: 2025-01-02 | W51: 0
A52: #ORD-10051 | B52: 2024-05-28 | C52: 17:32:49 | D52: Sebastian Lee | E52: sebastian.lee25@yahoo.com | F52: +1-237-229-9229 | G52: Milwaukee | H52: WI | I52: United States | J52: Classic Fit Polo Shirt x1 | K52: Apparel | L52: 1 | M52: 34.99 | N52: SAVE10 | O52: 3.5 | P52: 9.99 | Q52: 3.15 | R52: 44.63 | S52: Google Pay | T52: Online Store | U52: Fulfilled | V52: 2024-06-01 | W52: 0
A53: #ORD-10052 | B53: 2024-07-23 | C53: 06:13:09 | D53: Daniel Perez | E53: daniel.perez13@yahoo.com | F53: +1-890-979-9742 | G53: Milwaukee | H53: WI | I53: United States | J53: Wireless Noise-Cancelling Headphones x2 | Men's Grooming Kit x3 | Mechanical Keyboard x1 | Multivitamin Daily Pack x2 | K53: Electronics | L53: 4 | M53: 447.92 | N53: SAVE10 | O53: 44.79 | P53: 0 | Q53: 32.25 | R53: 435.38 | S53: PayPal | T53: Online Store | U53: Fulfilled | V53: 2024-07-26 | W53: 0
A54: #ORD-10053 | B54: 2024-07-29 | C54: 02:38:05 | D54: Elizabeth Lee | E54: elizabeth.lee92@yahoo.com | F54: +1-370-810-5906 | G54: Oklahoma City | H54: OK | I54: United States | J54: USB-C Fast Charger 65W x1 | K54: Electronics | L54: 1 | M54: 29.99 | N54: SAVE10 | O54: 3 | P54: 5.99 | Q54: 2.7 | R54: 35.68 | S54: Credit Card | T54: Referral | U54: Fulfilled | V54: 2024-08-02 | W54: 0
A55: #ORD-10054 | B55: 2024-05-25 | C55: 13:46:19 | D55: Liam Williams | E55: liam.williams8@gmail.com | F55: +1-834-799-4945 | G55: Austin | H55: TX | I55: United States | J55: Casual Sneakers x1 | K55: Footwear | L55: 1 | M55: 59.99 | N55: LOYALTY5 | O55: 3 | P55: 5.99 | Q55: 3.99 | R55: 66.97 | S55: Credit Card | T55: Facebook | U55: Unfulfilled | W55: 0
A56: #ORD-10055 | B56: 2024-04-08 | C56: 15:14:25 | D56: Michael Hill | E56: michael.hill30@gmail.com | F56: +1-506-754-7951 | G56: Phoenix | H56: AZ | I56: United States | J56: Anti-Aging Serum 1oz x2 | Wireless Noise-Cancelling Headphones x1 | K56: Beauty | L56: 2 | M56: 189.97 | N56: SAVE10 | O56: 19 | P56: 0 | Q56: 17.1 | R56: 188.07 | S56: Debit Card | T56: Online Store | U56: Partially Fulfilled | V56: 2024-04-13 | W56: 0
A57: #ORD-10056 | B57: 2024-05-29 | C57: 09:36:03 | D57: Harper Walker | E57: harper.walker39@gmail.com | F57: +1-779-985-1803 | G57: Milwaukee | H57: WI | I57: United States | J57: Smart LED Desk Lamp x1 | Casual Sneakers x1 | Protein Powder Chocolate 2lb x3 | K57: Electronics | L57: 3 | M57: 234.95 | N57: SAVE10 | O57: 23.5 | P57: 0 | Q57: 12.69 | R57: 224.14 | S57: Klarna | T57: Facebook | U57: Fulfilled | V57: 2024-05-30 | W57: 0
A58: #ORD-10057 | B58: 2024-11-07 | C58: 10:32:51 | D58: Victoria Allen | E58: victoria.allen37@yahoo.com | F58: +1-651-134-6977 | G58: Baltimore | H58: MD | I58: United States | J58: Essential Oil Diffuser x1 | K58: Home & Living | L58: 1 | M58: 32.99 | N58: SAVE10 | O58: 3.3 | P58: 5.99 | Q58: 2.97 | R58: 38.65 | S58: Credit Card | T58: Facebook | U58: Fulfilled | V58: 2024-11-10 | W58: 0
A59: #ORD-10058 | B59: 2024-06-10 | C59: 08:46:10 | D59: Isabella Garcia | E59: isabella.garcia38@gmail.com | F59: +1-693-925-5835 | G59: Tucson | H59: AZ | I59: United States | J59: Mechanical Keyboard x2 | K59: Electronics | L59: 1 | M59: 239.98 | N59: SAVE10 | O59: 24 | P59: 0 | Q59: 19.44 | R59: 235.42 | S59: Debit Card | T59: Online Store | U59: Fulfilled | V59: 2024-06-13 | W59: 0
A60: #ORD-10059 | B60: 2024-03-28 | C60: 14:52:52 | D60: Muhammad Davis | E60: muhammad.davis10@gmail.com | F60: +1-798-490-7086 | G60: Charlotte | H60: NC | I60: United States | J60: Men's Grooming Kit x3 | Anti-Aging Serum 1oz x2 | Protein Powder Chocolate 2lb x1 | K60: Beauty | L60: 3 | M60: 252.94 | N60: WELCOME15 | O60: 37.94 | P60: 0 | Q60: 12.9 | R60: 227.9 | S60: Credit Card | T60: Online Store | U60: Partially Fulfilled | V60: 2024-03-31 | W60: 0
A61: #ORD-10060 | B61: 2024-05-07 | C61: 09:14:24 | D61: Sophia Anderson | E61: sophia.anderson4@outlook.com | F61: +1-750-238-7367 | G61: Indianapolis | H61: IN | I61: United States | J61: Casual Sneakers x1 | Essential Oil Diffuser x2 | USB-C Fast Charger 65W x1 | Denim Jacket x1 | K61: Footwear | L61: 4 | M61: 220.95 | N61: None | O61: 0 | P61: 0 | Q61: 13.26 | R61: 234.21 | S61: Credit Card | T61: Instagram | U61: Fulfilled | V61: 2024-05-09 | W61: 0
A62: #ORD-10061 | B62: 2024-08-16 | C62: 02:24:31 | D62: Sebastian White | E62: sebastian.white96@outlook.com | F62: +1-441-975-6942 | G62: El Paso | H62: TX | I62: United States | J62: Mechanical Keyboard x1 | Leather Wallet Slim x2 | Multivitamin Daily Pack x1 | K62: Electronics | L62: 3 | M62: 199.96 | N62: SAVE10 | O62: 20 | P62: 0 | Q62: 10.8 | R62: 190.76 | S62: PayPal | T62: Online Store | U62: Cancelled | W62: 0
A63: #ORD-10062 | B63: 2024-06-03 | C63: 14:55:49 | D63: Sophia White | E63: sophia.white83@gmail.com | F63: +1-541-349-3063 | G63: Seattle | H63: WA | I63: United States | J63: Smart LED Desk Lamp x3 | K63: Electronics | L63: 1 | M63: 119.97 | N63: SUMMER20 | O63: 23.99 | P63: 0 | Q63: 5.76 | R63: 101.74 | S63: PayPal | T63: Facebook | U63: Fulfilled | V63: 2024-06-04 | W63: 0
A64: #ORD-10063 | B64: 2024-11-11 | C64: 18:12:10 | D64: Chloe Wilson | E64: chloe.wilson98@outlook.com | F64: +1-334-115-6869 | G64: Chicago | H64: IL | I64: United States | J64: Resistance Band Set x2 | Classic Fit Polo Shirt x1 | Mechanical Keyboard x1 | K64: Sports & Fitness | L64: 3 | M64: 204.96 | N64: None | O64: 0 | P64: 0 | Q64: 14.35 | R64: 219.31 | S64: Debit Card | T64: Email Campaign | U64: Fulfilled | V64: 2024-11-12 | W64: 0
A65: #ORD-10064 | B65: 2024-01-21 | C65: 08:23:39 | D65: Oliver Hill | E65: oliver.hill3@gmail.com | F65: +1-715-326-1710 | G65: Austin | H65: TX | I65: United States | J65: Multivitamin Daily Pack x1 | K65: Health & Nutrition | L65: 1 | M65: 19.99 | N65: None | O65: 0 | P65: 9.99 | Q65: 1.7 | R65: 31.68 | S65: Shop Pay | T65: Instagram | U65: Fulfilled | V65: 2024-01-25 | W65: 0
A66: #ORD-10065 | B66: 2024-07-05 | C66: 00:26:05 | D66: Owen Martin | E66: owen.martin83@yahoo.com | F66: +1-848-699-9984 | G66: Charlotte | H66: NC | I66: United States | J66: Multivitamin Daily Pack x1 | Anti-Aging Serum 1oz x2 | Smart LED Desk Lamp x1 | K66: Health & Nutrition | L66: 3 | M66: 159.96 | N66: None | O66: 0 | P66: 0 | Q66: 12.8 | R66: 172.76 | S66: PayPal | T66: Online Store | U66: Fulfilled | V66: 2024-07-10 | W66: 0
A67: #ORD-10066 | B67: 2024-07-15 | C67: 08:04:39 | D67: Abigail Harris | E67: abigail.harris68@gmail.com | F67: +1-547-947-8430 | G67: Nashville | H67: TN | I67: United States | J67: Smart LED Desk Lamp x2 | High-Waist Leggings x2 | K67: Electronics | L67: 2 | M67: 165.96 | N67: FLASH25 | O67: 41.49 | P67: 0 | Q67: 12.45 | R67: 136.92 | S67: Apple Pay | T67: Instagram | U67: Fulfilled | V67: 2024-07-19 | W67: 0
A68: #ORD-10067 | B68: 2024-05-01 | C68: 08:55:50 | D68: Henry Clark | E68: henry.clark13@gmail.com | F68: +1-769-161-6400 | G68: Portland | H68: OR | I68: United States | J68: Insulated Water Bottle 32oz x1 | Mechanical Keyboard x1 | K68: Sports & Fitness | L68: 2 | M68: 147.98 | N68: None | O68: 0 | P68: 0 | Q68: 8.88 | R68: 156.86 | S68: Credit Card | T68: Online Store | U68: Partially Fulfilled | V68: 2024-05-03 | W68: 0
A69: #ORD-10068 | B69: 2024-12-21 | C69: 16:16:54 | D69: Mason Clark | E69: mason.clark86@yahoo.com | F69: +1-769-476-2882 | G69: Jacksonville | H69: FL | I69: United States | J69: Yoga Mat Premium x1 | Scented Soy Candle Set x1 | K69: Sports & Fitness | L69: 2 | M69: 57.98 | N69: FLASH25 | O69: 14.5 | P69: 5.99 | Q69: 3.04 | R69: 52.51 | S69: PayPal | T69: Online Store | U69: Fulfilled | V69: 2024-12-24 | W69: 0
A70: #ORD-10069 | B70: 2024-11-13 | C70: 20:17:28 | D70: Elijah Nguyen | E70: elijah.nguyen55@outlook.com | F70: +1-559-106-3972 | G70: San Diego | H70: CA | I70: United States | J70: Anti-Aging Serum 1oz x1 | Essential Oil Diffuser x1 | K70: Beauty | L70: 2 | M70: 82.98 | N70: SAVE10 | O70: 8.3 | P70: 0 | Q70: 4.48 | R70: 79.16 | S70: Credit Card | T70: Google Shopping | U70: Fulfilled | V70: 2024-11-16 | W70: 0
A71: #ORD-10070 | B71: 2024-10-14 | C71: 18:19:55 | D71: James Nguyen | E71: james.nguyen52@gmail.com | F71: +1-810-186-1861 | G71: El Paso | H71: TX | I71: United States | J71: Wireless Noise-Cancelling Headphones x2 | USB-C Fast Charger 65W x1 | K71: Electronics | L71: 2 | M71: 209.97 | N71: WELCOME15 | O71: 31.5 | P71: 0 | Q71: 15.17 | R71: 193.64 | S71: Credit Card | T71: Online Store | U71: Partially Fulfilled | V71: 2024-10-19 | W71: 0
A72: #ORD-10071 | B72: 2024-02-01 | C72: 16:23:41 | D72: James Hernandez | E72: james.hernandez80@gmail.com | F72: +1-640-213-5640 | G72: Memphis | H72: TN | I72: United States | J72: Anti-Aging Serum 1oz x1 | K72: Beauty | L72: 1 | M72: 49.99 | N72: LOYALTY5 | O72: 2.5 | P72: 9.99 | Q72: 4.04 | R72: 61.52 | S72: Credit Card | T72: Google Shopping | U72: Fulfilled | V72: 2024-02-04 | W72: 0
A73: #ORD-10072 | B73: 2024-03-26 | C73: 15:22:50 | D73: Daniel Allen | E73: daniel.allen86@gmail.com | F73: +1-322-107-9149 | G73: San Francisco | H73: CA | I73: United States | J73: Scented Soy Candle Set x1 | K73: Home & Living | L73: 1 | M73: 22.99 | N73: None | O73: 0 | P73: 7.99 | Q73: 1.61 | R73: 32.59 | S73: Shop Pay | T73: Google Shopping | U73: Fulfilled | V73: 2024-03-29 | W73: 0
A74: #ORD-10073 | B74: 2024-08-04 | C74: 23:40:51 | D74: Jack Lopez | E74: jack.lopez49@yahoo.com | F74: +1-926-755-7843 | G74: Phoenix | H74: AZ | I74: United States | J74: High-Waist Leggings x1 | Insulated Water Bottle 32oz x2 | USB-C Fast Charger 65W x1 | K74: Apparel | L74: 3 | M74: 128.96 | N74: SUMMER20 | O74: 25.79 | P74: 0 | Q74: 6.19 | R74: 109.36 | S74: Apple Pay | T74: Facebook | U74: Unfulfilled | W74: 0
A75: #ORD-10074 | B75: 2024-08-28 | C75: 01:20:42 | D75: Evelyn Davis | E75: evelyn.davis3@yahoo.com | F75: +1-517-863-6562 | G75: Fort Worth | H75: TX | I75: United States | J75: Sunscreen SPF 50 Face x1 | Bamboo Sunglasses x1 | K75: Beauty | L75: 2 | M75: 43.98 | N75: None | O75: 0 | P75: 5.99 | Q75: 3.74 | R75: 53.71 | S75: PayPal | T75: Instagram | U75: Unfulfilled | W75: 0
A76: #ORD-10075 | B76: 2024-09-02 | C76: 22:04:54 | D76: Amelia Perez | E76: amelia.perez22@gmail.com | F76: +1-305-249-5193 | G76: Memphis | H76: TN | I76: United States | J76: Air Fryer 5.8Qt x1 | K76: Kitchen | L76: 1 | M76: 79.99 | N76: SAVE10 | O76: 8 | P76: 0 | Q76: 5.76 | R76: 77.75 | S76: PayPal | T76: Email Campaign | U76: Fulfilled | V76: 2024-09-04 | W76: 0
A77: #ORD-10076 | B77: 2024-03-09 | C77: 19:07:17 | D77: Charlotte Lopez | E77: charlotte.lopez20@outlook.com | F77: +1-269-580-8245 | G77: Nashville | H77: TN | I77: United States | J77: Essential Oil Diffuser x1 | Stainless Steel Cookware Set x1 | Organic Green Tea 100ct x1 | Classic Fit Polo Shirt x2 | K77: Home & Living | L77: 4 | M77: 247.95 | N77: LOYALTY5 | O77: 12.4 | P77: 0 | Q77: 18.84 | R77: 254.39 | S77: Apple Pay | T77: Facebook | U77: Fulfilled | V77: 2024-03-13 | W77: 0
A78: #ORD-10077 | B78: 2024-01-29 | C78: 19:30:25 | D78: Aiden Moore | E78: aiden.moore8@gmail.com | F78: +1-808-619-7299 | G78: Denver | H78: CO | I78: United States | J78: Organic Green Tea 100ct x1 | K78: Food & Beverage | L78: 1 | M78: 14.99 | N78: SAVE10 | O78: 1.5 | P78: 7.99 | Q78: 0.81 | R78: 22.29 | S78: PayPal | T78: Referral | U78: Fulfilled | V78: 2024-02-03 | W78: 0
A79: #ORD-10078 | B79: 2024-11-10 | C79: 12:01:53 | D79: Sebastian Hill | E79: sebastian.hill95@yahoo.com | F79: +1-716-761-3827 | G79: Seattle | H79: WA | I79: United States | J79: Running Shoes - Women's x1 | Resistance Band Set x1 | K79: Footwear | L79: 2 | M79: 94.98 | N79: None | O79: 0 | P79: 0 | Q79: 8.07 | R79: 103.05 | S79: Credit Card | T79: Direct | U79: Partially Fulfilled | V79: 2024-11-11 | W79: 0
A80: #ORD-10079 | B80: 2024-08-24 | C80: 19:47:54 | D80: Olivia Thomas | E80: olivia.thomas57@outlook.com | F80: +1-537-196-7333 | G80: Boston | H80: MA | I80: United States | J80: Insulated Water Bottle 32oz x2 | K80: Sports & Fitness | L80: 1 | M80: 55.98 | N80: WELCOME15 | O80: 8.4 | P80: 9.99 | Q80: 3.81 | R80: 61.38 | S80: PayPal | T80: Online Store | U80: Partially Fulfilled | V80: 2024-08-25 | W80: 0
A81: #ORD-10080 | B81: 2024-02-28 | C81: 09:34:51 | D81: Evelyn Taylor | E81: evelyn.taylor85@outlook.com | F81: +1-772-485-6381 | G81: Portland | H81: OR | I81: United States | J81: Linen Throw Blanket x1 | K81: Home & Living | L81: 1 | M81: 39.99 | N81: SAVE10 | O81: 4 | P81: 7.99 | Q81: 3.6 | R81: 47.58 | S81: PayPal | T81: Online Store | U81: Fulfilled | V81: 2024-03-02 | W81: 0
A82: #ORD-10081 | B82: 2024-01-08 | C82: 01:55:15 | D82: Isabella Wright | E82: isabella.wright83@outlook.com | F82: +1-502-964-2657 | G82: Chicago | H82: IL | I82: United States | J82: Running Shoes - Men's x3 | K82: Footwear | L82: 1 | M82: 224.97 | N82: SAVE10 | O82: 22.5 | P82: 0 | Q82: 17.21 | R82: 219.68 | S82: Credit Card | T82: Referral | U82: Fulfilled | V82: 2024-01-09 | W82: 0
A83: #ORD-10082 | B83: 2024-05-10 | C83: 18:52:17 | D83: Scarlett Scott | E83: scarlett.scott95@yahoo.com | F83: +1-654-725-5668 | G83: Baltimore | H83: MD | I83: United States | J83: Scented Soy Candle Set x1 | Mechanical Keyboard x1 | Protein Powder Chocolate 2lb x1 | K83: Home & Living | L83: 3 | M83: 187.97 | N83: LOYALTY5 | O83: 9.4 | P83: 0 | Q83: 12.5 | R83: 191.07 | S83: PayPal | T83: Online Store | U83: Partially Fulfilled | V83: 2024-05-12 | W83: 0
A84: #ORD-10083 | B84: 2024-11-10 | C84: 00:55:14 | D84: Avery Anderson | E84: avery.anderson31@gmail.com | F84: +1-365-936-4271 | G84: Seattle | H84: WA | I84: United States | J84: Leather Wallet Slim x1 | Denim Jacket x3 | Running Shoes - Women's x3 | K84: Bags & Accessories | L84: 3 | M84: 434.93 | N84: SUMMER20 | O84: 86.99 | P84: 0 | Q84: 27.84 | R84: 375.78 | S84: Shop Pay | T84: Instagram | U84: Unfulfilled | W84: 0
A85: #ORD-10084 | B85: 2024-07-05 | C85: 15:25:46 | D85: Victoria Rodriguez | E85: victoria.rodriguez33@gmail.com | F85: +1-293-327-8391 | G85: Milwaukee | H85: WI | I85: United States | J85: Coffee Maker Programmable x2 | Bamboo Sunglasses x1 | Smart LED Desk Lamp x1 | K85: Kitchen | L85: 3 | M85: 174.96 | N85: None | O85: 0 | P85: 0 | Q85: 12.25 | R85: 187.21 | S85: Credit Card | T85: Direct | U85: Fulfilled | V85: 2024-07-09 | W85: 0
A86: #ORD-10085 | B86: 2024-05-25 | C86: 05:34:25 | D86: Emily Johnson | E86: emily.johnson7@gmail.com | F86: +1-239-393-8740 | G86: Columbus | H86: OH | I86: United States | J86: USB-C Fast Charger 65W x1 | K86: Electronics | L86: 1 | M86: 29.99 | N86: None | O86: 0 | P86: 7.99 | Q86: 1.8 | R86: 39.78 | S86: Apple Pay | T86: Facebook | U86: Fulfilled | V86: 2024-05-27 | W86: 0
A87: #ORD-10086 | B87: 2024-01-31 | C87: 18:26:15 | D87: Isabella Young | E87: isabella.young79@gmail.com | F87: +1-508-224-1782 | G87: Charlotte | H87: NC | I87: United States | J87: Running Shoes - Women's x2 | K87: Footwear | L87: 1 | M87: 139.98 | N87: FLASH25 | O87: 34.99 | P87: 0 | Q87: 10.5 | R87: 115.49 | S87: PayPal | T87: Instagram | U87: Fulfilled | V87: 2024-02-02 | W87: 0
A88: #ORD-10087 | B88: 2024-02-13 | C88: 01:16:13 | D88: Oliver Clark | E88: oliver.clark80@gmail.com | F88: +1-626-291-2402 | G88: Oklahoma City | H88: OK | I88: United States | J88: Stainless Steel Cookware Set x1 | Scented Soy Candle Set x1 | Coffee Maker Programmable x1 | K88: Kitchen | L88: 3 | M88: 207.97 | N88: None | O88: 0 | P88: 0 | Q88: 16.64 | R88: 224.61 | S88: Debit Card | T88: Facebook | U88: Fulfilled | V88: 2024-02-18 | W88: 0
A89: #ORD-10088 | B89: 2024-07-16 | C89: 03:23:07 | D89: Owen White | E89: owen.white68@outlook.com | F89: +1-446-850-2698 | G89: Chicago | H89: IL | I89: United States | J89: Protein Powder Chocolate 2lb x1 | Canvas Backpack 25L x1 | K89: Health & Nutrition | L89: 2 | M89: 99.98 | N89: SAVE10 | O89: 10 | P89: 0 | Q89: 7.2 | R89: 97.18 | S89: Shop Pay | T89: Online Store | U89: Fulfilled | V89: 2024-07-19 | W89: 0
A90: #ORD-10089 | B90: 2024-05-11 | C90: 11:29:20 | D90: Daniel Perez | E90: daniel.perez6@gmail.com | F90: +1-237-400-4302 | G90: Phoenix | H90: AZ | I90: United States | J90: Running Shoes - Men's x1 | Denim Jacket x3 | Classic Fit Polo Shirt x1 | K90: Footwear | L90: 3 | M90: 304.95 | N90: None | O90: 0 | P90: 0 | Q90: 21.35 | R90: 326.3 | S90: Credit Card | T90: Email Campaign | U90: Cancelled | W90: 0
A91: #ORD-10090 | B91: 2024-04-30 | C91: 10:07:00 | D91: Olivia Gonzalez | E91: olivia.gonzalez6@gmail.com | F91: +1-327-918-7029 | G91: Albuquerque | H91: NM | I91: United States | J91: Denim Jacket x1 | Coffee Maker Programmable x1 | K91: Apparel | L91: 2 | M91: 119.98 | N91: None | O91: 0 | P91: 0 | Q91: 9.6 | R91: 129.58 | S91: Debit Card | T91: Email Campaign | U91: Partially Fulfilled | V91: 2024-05-03 | W91: 0
A92: #ORD-10091 | B92: 2024-03-13 | C92: 13:15:45 | D92: Jack Sanchez | E92: jack.sanchez57@yahoo.com | F92: +1-500-428-2680 | G92: Portland | H92: OR | I92: United States | J92: Stainless Steel Cookware Set x3 | Insulated Water Bottle 32oz x1 | K92: Kitchen | L92: 2 | M92: 417.96 | N92: None | O92: 0 | P92: 0 | Q92: 41.8 | R92: 459.76 | S92: Debit Card | T92: Instagram | U92: Fulfilled | V92: 2024-03-18 | W92: 0
A93: #ORD-10092 | B93: 2024-08-22 | C93: 00:50:26 | D93: Ethan Lee | E93: ethan.lee38@gmail.com | F93: +1-887-752-7655 | G93: El Paso | H93: TX | I93: United States | J93: Running Shoes - Men's x1 | Sunscreen SPF 50 Face x1 | K93: Footwear | L93: 2 | M93: 93.98 | N93: SAVE10 | O93: 9.4 | P93: 0 | Q93: 7.61 | R93: 92.19 | S93: Afterpay | T93: Online Store | U93: Fulfilled | V93: 2024-08-23 | W93: 0
A94: #ORD-10093 | B94: 2024-02-25 | C94: 10:48:03 | D94: Alexander King | E94: alexander.king96@outlook.com | F94: +1-579-480-8273 | G94: Louisville | H94: KY | I94: United States | J94: Anti-Aging Serum 1oz x1 | High-Waist Leggings x1 | Organic Green Tea 100ct x2 | K94: Beauty | L94: 3 | M94: 122.96 | N94: SAVE10 | O94: 12.3 | P94: 0 | Q94: 8.85 | R94: 119.51 | S94: Debit Card | T94: Facebook | U94: Fulfilled | V94: 2024-02-29 | W94: 0
A95: #ORD-10094 | B95: 2024-05-02 | C95: 02:17:04 | D95: Ava Nguyen | E95: ava.nguyen68@gmail.com | F95: +1-419-726-5678 | G95: Phoenix | H95: AZ | I95: United States | J95: Casual Sneakers x1 | Smart LED Desk Lamp x1 | K95: Footwear | L95: 2 | M95: 99.98 | N95: FLASH25 | O95: 25 | P95: 0 | Q95: 6.37 | R95: 81.35 | S95: Google Pay | T95: Online Store | U95: Fulfilled | V95: 2024-05-06 | W95: 0
A96: #ORD-10095 | B96: 2024-12-15 | C96: 00:17:44 | D96: Michael Gonzalez | E96: michael.gonzalez18@yahoo.com | F96: +1-507-971-3580 | G96: Houston | H96: TX | I96: United States | J96: USB-C Fast Charger 65W x1 | High-Waist Leggings x2 | K96: Electronics | L96: 2 | M96: 115.97 | N96: SAVE10 | O96: 11.6 | P96: 0 | Q96: 10.44 | R96: 114.81 | S96: Credit Card | T96: Online Store | U96: Refunded | V96: 2024-12-18 | W96: 114.81
A97: #ORD-10096 | B97: 2024-03-19 | C97: 01:16:22 | D97: Logan White | E97: logan.white29@gmail.com | F97: +1-934-836-8842 | G97: San Francisco | H97: CA | I97: United States | J97: Casual Sneakers x1 | High-Waist Leggings x1 | Stainless Steel Cookware Set x1 | K97: Footwear | L97: 3 | M97: 232.97 | N97: FLASH25 | O97: 58.24 | P97: 0 | Q97: 12.23 | R97: 186.96 | S97: PayPal | T97: Online Store | U97: Fulfilled | V97: 2024-03-23 | W97: 0
A98: #ORD-10097 | B98: 2024-05-03 | C98: 02:54:43 | D98: Owen Clark | E98: owen.clark53@yahoo.com | F98: +1-730-256-5982 | G98: Memphis | H98: TN | I98: United States | J98: Organic Green Tea 100ct x1 | Anti-Aging Serum 1oz x1 | K98: Food & Beverage | L98: 2 | M98: 64.98 | N98: FLASH25 | O98: 16.25 | P98: 5.99 | Q98: 3.41 | R98: 58.13 | S98: Debit Card | T98: Direct | U98: Fulfilled | V98: 2024-05-04 | W98: 0
A99: #ORD-10098 | B99: 2024-12-31 | C99: 09:51:41 | D99: Mia Hernandez | E99: mia.hernandez91@gmail.com | F99: +1-714-756-3762 | G99: Austin | H99: TX | I99: United States | J99: Yoga Mat Premium x1 | Canvas Backpack 25L x1 | K99: Sports & Fitness | L99: 2 | M99: 89.98 | N99: FLASH25 | O99: 22.5 | P99: 0 | Q99: 5.4 | R99: 72.88 | S99: Credit Card | T99: Online Store | U99: Refunded | V99: 2025-01-01 | W99: 72.88
A100: #ORD-10099 | B100: 2024-08-23 | C100: 00:18:12 | D100: Daniel Hill | E100: daniel.hill22@outlook.com | F100: +1-985-685-7825 | G100: Phoenix | H100: AZ | I100: United States | J100: Bamboo Sunglasses x1 | K100: Bags & Accessories | L100: 1 | M100: 24.99 | N100: None | O100: 0 | P100: 4.99 | Q100: 1.5 | R100: 31.48 | S100: Google Pay | T100: Email Campaign | U100: Fulfilled | V100: 2024-08-25 | W100: 0
...

Sheet Orders_Clean
A1: Order ID | B1: Order Date | C1: Order Time | D1: Customer Name | E1: Email | F1: Phone | G1: City | H1: State | I1: Country | J1: Line Items | K1: Primary Category | L1: Total Items | M1: Subtotal ($) | N1: Discount Code | O1: Discount Amount ($) | P1: Shipping ($) | Q1: Tax ($) | R1: Order Total ($) | S1: Payment Method | T1: Sales Channel | U1: Fulfillment Status | V1: Fulfillment Date | W1: Refund Amount ($) | X1: Month Name | Y1: Quarter | Z1: Net Revenue
A2: #ORD-10001 | B2: 2024-02-24 | C2: 04:35:15 | D2: Mason Johnson | E2: mason.johnson36@gmail.com | F2: +1-933-765-9928 | G2: Portland | H2: OR | I2: United States | J2: Anti-Aging Serum 1oz x1 | Men's Grooming Kit x1 | Leather Wallet Slim x1 | K2: Beauty | L2: 3 | M2: 115.97 | N2: None | O2: 0 | P2: 0 | Q2: 8.12 | R2: 124.09 | S2: Credit Card | T2: Facebook | U2: Refunded | V2: 2024-02-26 | W2: 124.09 | X2: =TEXT(B2,"MMMM") -> February | Y2: =IF(MONTH(B2)<=3,"Q1",IF(MONTH(B2)<=6,"Q2",IF(MONTH(B2)<=9,"Q3","Q4"))) -> Q1 | Z2: =M2-O2 -> 115.97
A3: #ORD-10002 | B3: 2024-12-03 | C3: 14:27:58 | D3: Sofia Anderson | E3: sofia.anderson76@gmail.com | F3: +1-294-489-2584 | G3: Charlotte | H3: NC | I3: United States | J3: High-Waist Leggings x1 | K3: Apparel | L3: 1 | M3: 42.99 | N3: WELCOME15 | O3: 6.45 | P3: 7.99 | Q3: 2.92 | R3: 47.45 | S3: Credit Card | T3: TikTok Shop | U3: Partially Fulfilled | V3: 2024-12-04 | W3: 0 | X3: =TEXT(B3,"MMMM") -> December | Y3: =IF(MONTH(B3)<=3,"Q1",IF(MONTH(B3)<=6,"Q2",IF(MONTH(B3)<=9,"Q3","Q4"))) -> Q4 | Z3: =M3-O3 -> 36.54
A4: #ORD-10003 | B4: 2024-07-27 | C4: 06:00:29 | D4: Emily Thompson | E4: emily.thompson34@outlook.com | F4: +1-246-777-4733 | G4: Nashville | H4: TN | I4: United States | J4: Bamboo Sunglasses x1 | K4: Bags & Accessories | L4: 1 | M4: 24.99 | N4: FLASH25 | O4: 6.25 | P4: 7.99 | Q4: 1.87 | R4: 28.6 | S4: PayPal | T4: Direct | U4: Fulfilled | V4: 2024-07-28 | W4: 0 | X4: =TEXT(B4,"MMMM") -> July | Y4: =IF(MONTH(B4)<=3,"Q1",IF(MONTH(B4)<=6,"Q2",IF(MONTH(B4)<=9,"Q3","Q4"))) -> Q3 | Z4: =M4-O4 -> 18.74
A5: #ORD-10004 | B5: 2024-06-25 | C5: 02:05:25 | D5: Evelyn Garcia | E5: evelyn.garcia30@yahoo.com | F5: +1-946-350-3677 | G5: Milwaukee | H5: WI | I5: United States | J5: Insulated Water Bottle 32oz x1 | Running Shoes - Men's x1 | K5: Sports & Fitness | L5: 2 | M5: 102.98 | N5: SAVE10 | O5: 10.3 | P5: 0 | Q5: 9.27 | R5: 101.95 | S5: Google Pay | T5: Facebook | U5: Fulfilled | V5: 2024-06-30 | W5: 0 | X5: =TEXT(B5,"MMMM") -> June | Y5: =IF(MONTH(B5)<=3,"Q1",IF(MONTH(B5)<=6,"Q2",IF(MONTH(B5)<=9,"Q3","Q4"))) -> Q2 | Z5: =M5-O5 -> 92.68
A6: #ORD-10005 | B6: 2024-05-05 | C6: 22:32:02 | D6: Sebastian Harris | E6: sebastian.harris82@yahoo.com | F6: +1-871-611-7482 | G6: Dallas | H6: TX | I6: United States | J6: Classic Fit Polo Shirt x2 | Portable Bluetooth Speaker x2 | Casual Sneakers x1 | K6: Apparel | L6: 3 | M6: 229.95 | N6: None | O6: 0 | P6: 0 | Q6: 16.1 | R6: 246.05 | S6: Google Pay | T6: Facebook | U6: Partially Fulfilled | V6: 2024-05-07 | W6: 0 | X6: =TEXT(B6,"MMMM") -> May | Y6: =IF(MONTH(B6)<=3,"Q1",IF(MONTH(B6)<=6,"Q2",IF(MONTH(B6)<=9,"Q3","Q4"))) -> Q2 | Z6: =M6-O6 -> 229.95
A7: #ORD-10006 | B7: 2024-08-06 | C7: 00:19:48 | D7: Sebastian Martinez | E7: sebastian.martinez18@gmail.com | F7: +1-293-873-1771 | G7: Dallas | H7: TX | I7: United States | J7: Men's Grooming Kit x1 | Linen Throw Blanket x1 | K7: Beauty | L7: 2 | M7: 75.98 | N7: SAVE10 | O7: 7.6 | P7: 0 | Q7: 4.79 | R7: 73.17 | S7: Afterpay | T7: Online Store | U7: Cancelled | W7: 0 | X7: =TEXT(B7,"MMMM") -> August | Y7: =IF(MONTH(B7)<=3,"Q1",IF(MONTH(B7)<=6,"Q2",IF(MONTH(B7)<=9,"Q3","Q4"))) -> Q3 | Z7: =M7-O7 -> 68.38
A8: #ORD-10007 | B8: 2024-01-25 | C8: 16:07:16 | D8: Mason Martinez | E8: mason.martinez21@yahoo.com | F8: +1-968-373-6573 | G8: Oklahoma City | H8: OK | I8: United States | J8: Scented Soy Candle Set x3 | K8: Home & Living | L8: 1 | M8: 68.97 | N8: FLASH25 | O8: 17.24 | P8: 7.99 | Q8: 4.66 | R8: 64.38 | S8: Apple Pay | T8: Online Store | U8: Fulfilled | V8: 2024-01-30 | W8: 0 | X8: =TEXT(B8,"MMMM") -> January | Y8: =IF(MONTH(B8)<=3,"Q1",IF(MONTH(B8)<=6,"Q2",IF(MONTH(B8)<=9,"Q3","Q4"))) -> Q1 | Z8: =M8-O8 -> 51.73
A9: #ORD-10008 | B9: 2024-10-07 | C9: 10:23:08 | D9: Mason Jackson | E9: mason.jackson21@gmail.com | F9: +1-752-897-9689 | G9: Columbus | H9: OH | I9: United States | J9: Hiking Boots x1 | Air Fryer 5.8Qt x2 | Classic Fit Polo Shirt x2 | K9: Footwear | L9: 3 | M9: 339.95 | N9: SAVE10 | O9: 33.99 | P9: 0 | Q9: 30.6 | R9: 336.56 | S9: Debit Card | T9: Online Store | U9: Partially Fulfilled | V9: 2024-10-09 | W9: 0 | X9: =TEXT(B9,"MMMM") -> October | Y9: =IF(MONTH(B9)<=3,"Q1",IF(MONTH(B9)<=6,"Q2",IF(MONTH(B9)<=9,"Q3","Q4"))) -> Q4 | Z9: =M9-O9 -> 305.96
A10: #ORD-10009 | B10: 2024-12-26 | C10: 19:49:36 | D10: Emma Flores | E10: emma.flores63@gmail.com | F10: +1-949-597-2133 | G10: Austin | H10: TX | I10: United States | J10: Denim Jacket x2 | K10: Apparel | L10: 1 | M10: 129.98 | N10: None | O10: 0 | P10: 0 | Q10: 7.8 | R10: 137.78 | S10: Credit Card | T10: Facebook | U10: Fulfilled | V10: 2024-12-27 | W10: 0 | X10: =TEXT(B10,"MMMM") -> December | Y10: =IF(MONTH(B10)<=3,"Q1",IF(MONTH(B10)<=6,"Q2",IF(MONTH(B10)<=9,"Q3","Q4"))) -> Q4 | Z10: =M10-O10 -> 129.98
A11: #ORD-10010 | B11: 2024-08-01 | C11: 12:32:27 | D11: Grace Rodriguez | E11: grace.rodriguez85@gmail.com | F11: +1-608-787-7118 | G11: Phoenix | H11: AZ | I11: United States | J11: Air Fryer 5.8Qt x2 | K11: Kitchen | L11: 1 | M11: 159.98 | N11: WELCOME15 | O11: 24 | P11: 0 | Q11: 9.52 | R11: 145.5 | S11: Google Pay | T11: Google Shopping | U11: Fulfilled | V11: 2024-08-04 | W11: 0 | X11: =TEXT(B11,"MMMM") -> August | Y11: =IF(MONTH(B11)<=3,"Q1",IF(MONTH(B11)<=6,"Q2",IF(MONTH(B11)<=9,"Q3","Q4"))) -> Q3 | Z11: =M11-O11 -> 135.98
A12: #ORD-10011 | B12: 2024-01-25 | C12: 20:45:52 | D12: Avery Wright | E12: avery.wright16@gmail.com | F12: +1-232-980-6413 | G12: Charlotte | H12: NC | I12: United States | J12: Linen Throw Blanket x1 | K12: Home & Living | L12: 1 | M12: 39.99 | N12: LOYALTY5 | O12: 2 | P12: 5.99 | Q12: 2.28 | R12: 46.26 | S12: Credit Card | T12: Facebook | U12: Fulfilled | V12: 2024-01-26 | W12: 0 | X12: =TEXT(B12,"MMMM") -> January | Y12: =IF(MONTH(B12)<=3,"Q1",IF(MONTH(B12)<=6,"Q2",IF(MONTH(B12)<=9,"Q3","Q4"))) -> Q1 | Z12: =M12-O12 -> 37.99
A13: #ORD-10012 | B13: 2024-02-21 | C13: 09:14:08 | D13: Ava King | E13: ava.king36@yahoo.com | F13: +1-620-578-1887 | G13: San Diego | H13: CA | I13: United States | J13: Leather Wallet Slim x1 | Linen Throw Blanket x1 | K13: Bags & Accessories | L13: 2 | M13: 69.98 | N13: SUMMER20 | O13: 14 | P13: 9.99 | Q13: 3.92 | R13: 69.89 | S13: Credit Card | T13: Facebook | U13: Partially Fulfilled | V13: 2024-02-25 | W13: 0 | X13: =TEXT(B13,"MMMM") -> February | Y13: =IF(MONTH(B13)<=3,"Q1",IF(MONTH(B13)<=6,"Q2",IF(MONTH(B13)<=9,"Q3","Q4"))) -> Q1 | Z13: =M13-O13 -> 55.98
A14: #ORD-10013 | B14: 2024-11-30 | C14: 15:22:12 | D14: Sophia Brown | E14: sophia.brown94@gmail.com | F14: +1-763-200-1828 | G14: Fort Worth | H14: TX | I14: United States | J14: Running Shoes - Women's x1 | K14: Footwear | L14: 1 | M14: 69.99 | N14: SUMMER20 | O14: 14 | P14: 5.99 | Q14: 4.76 | R14: 66.74 | S14: Credit Card | T14: Instagram | U14: Fulfilled | V14: 2024-12-04 | W14: 0 | X14: =TEXT(B14,"MMMM") -> November | Y14: =IF(MONTH(B14)<=3,"Q1",IF(MONTH(B14)<=6,"Q2",IF(MONTH(B14)<=9,"Q3","Q4"))) -> Q4 | Z14: =M14-O14 -> 55.99
A15: #ORD-10014 | B15: 2024-07-07 | C15: 14:30:12 | D15: Grace Smith | E15: grace.smith97@yahoo.com | F15: +1-492-533-8973 | G15: Chicago | H15: IL | I15: United States | J15: Canvas Backpack 25L x2 | Protein Powder Chocolate 2lb x1 | K15: Bags & Accessories | L15: 2 | M15: 154.97 | N15: None | O15: 0 | P15: 0 | Q15: 13.17 | R15: 168.14 | S15: Credit Card | T15: Email Campaign | U15: Cancelled | W15: 0 | X15: =TEXT(B15,"MMMM") -> July | Y15: =IF(MONTH(B15)<=3,"Q1",IF(MONTH(B15)<=6,"Q2",IF(MONTH(B15)<=9,"Q3","Q4"))) -> Q3 | Z15: =M15-O15 -> 154.97
A16: #ORD-10015 | B16: 2024-07-29 | C16: 13:37:32 | D16: James Gonzalez | E16: james.gonzalez28@outlook.com | F16: +1-282-971-4044 | G16: San Jose | H16: CA | I16: United States | J16: Resistance Band Set x1 | K16: Sports & Fitness | L16: 1 | M16: 24.99 | N16: LOYALTY5 | O16: 1.25 | P16: 9.99 | Q16: 2.14 | R16: 35.87 | S16: Google Pay | T16: Instagram | U16: Fulfilled | V16: 2024-08-03 | W16: 0 | X16: =TEXT(B16,"MMMM") -> July | Y16: =IF(MONTH(B16)<=3,"Q1",IF(MONTH(B16)<=6,"Q2",IF(MONTH(B16)<=9,"Q3","Q4"))) -> Q3 | Z16: =M16-O16 -> 23.74
A17: #ORD-10016 | B17: 2024-12-31 | C17: 16:18:43 | D17: Ava Flores | E17: ava.flores87@yahoo.com | F17: +1-334-787-5915 | G17: Chicago | H17: IL | I17: United States | J17: Casual Sneakers x1 | Linen Throw Blanket x1 | Scented Soy Candle Set x1 | Portable Bluetooth Speaker x1 | K17: Footwear | L17: 4 | M17: 172.96 | N17: SAVE10 | O17: 17.3 | P17: 0 | Q17: 10.9 | R17: 166.56 | S17: PayPal | T17: Online Store | U17: Fulfilled | V17: 2025-01-04 | W17: 0 | X17: =TEXT(B17,"MMMM") -> December | Y17: =IF(MONTH(B17)<=3,"Q1",IF(MONTH(B17)<=6,"Q2",IF(MONTH(B17)<=9,"Q3","Q4"))) -> Q4 | Z17: =M17-O17 -> 155.66
A18: #ORD-10017 | B18: 2024-08-29 | C18: 05:37:25 | D18: Sebastian Lee | E18: sebastian.lee97@yahoo.com | F18: +1-883-936-5905 | G18: Tucson | H18: AZ | I18: United States | J18: Smart LED Desk Lamp x1 | USB-C Fast Charger 65W x3 | Coffee Maker Programmable x2 | Running Shoes - Women's x2 | Air Fryer 5.8Qt x1 | K18: Electronics | L18: 5 | M18: 459.91 | N18: None | O18: 0 | P18: 0 | Q18: 39.09 | R18: 499 | S18: Apple Pay | T18: Google Shopping | U18: Refunded | V18: 2024-08-30 | W18: 499 | X18: =TEXT(B18,"MMMM") -> August | Y18: =IF(MONTH(B18)<=3,"Q1",IF(MONTH(B18)<=6,"Q2",IF(MONTH(B18)<=9,"Q3","Q4"))) -> Q3 | Z18: =M18-O18 -> 459.91
A19: #ORD-10018 | B19: 2024-03-01 | C19: 08:52:46 | D19: Sophia Rodriguez | E19: sophia.rodriguez15@outlook.com | F19: +1-457-966-1832 | G19: Dallas | H19: TX | I19: United States | J19: Scented Soy Candle Set x1 | K19: Home & Living | L19: 1 | M19: 22.99 | N19: SAVE10 | O19: 2.3 | P19: 5.99 | Q19: 2.07 | R19: 28.75 | S19: PayPal | T19: Online Store | U19: Cancelled | W19: 0 | X19: =TEXT(B19,"MMMM") -> March | Y19: =IF(MONTH(B19)<=3,"Q1",IF(MONTH(B19)<=6,"Q2",IF(MONTH(B19)<=9,"Q3","Q4"))) -> Q1 | Z19: =M19-O19 -> 20.69
A20: #ORD-10019 | B20: 2024-05-09 | C20: 12:58:20 | D20: Ethan Lewis | E20: ethan.lewis36@gmail.com | F20: +1-236-954-7049 | G20: Baltimore | H20: MD | I20: United States | J20: Essential Oil Diffuser x2 | Hiking Boots x1 | Running Shoes - Men's x1 | K20: Home & Living | L20: 3 | M20: 250.96 | N20: None | O20: 0 | P20: 0 | Q20: 15.06 | R20: 266.02 | S20: Credit Card | T20: Direct | U20: Fulfilled | V20: 2024-05-14 | W20: 0 | X20: =TEXT(B20,"MMMM") -> May | Y20: =IF(MONTH(B20)<=3,"Q1",IF(MONTH(B20)<=6,"Q2",IF(MONTH(B20)<=9,"Q3","Q4"))) -> Q2 | Z20: =M20-O20 -> 250.96
A21: #ORD-10020 | B21: 2024-04-29 | C21: 17:10:33 | D21: Daniel Torres | E21: daniel.torres56@gmail.com | F21: +1-616-735-3532 | G21: Phoenix | H21: AZ | I21: United States | J21: Bamboo Sunglasses x2 | K21: Bags & Accessories | L21: 1 | M21: 49.98 | N21: None | O21: 0 | P21: 7.99 | Q21: 3.5 | R21: 61.47 | S21: PayPal | T21: Facebook | U21: Partially Fulfilled | V21: 2024-05-04 | W21: 0 | X21: =TEXT(B21,"MMMM") -> April | Y21: =IF(MONTH(B21)<=3,"Q1",IF(MONTH(B21)<=6,"Q2",IF(MONTH(B21)<=9,"Q3","Q4"))) -> Q2 | Z21: =M21-O21 -> 49.98
A22: #ORD-10021 | B22: 2024-10-13 | C22: 01:16:42 | D22: Oliver Hernandez | E22: oliver.hernandez23@yahoo.com | F22: +1-671-458-6000 | G22: Louisville | H22: KY | I22: United States | J22: High-Waist Leggings x2 | Bamboo Sunglasses x2 | Multivitamin Daily Pack x1 | Anti-Aging Serum 1oz x2 | K22: Apparel | L22: 4 | M22: 255.93 | N22: None | O22: 0 | P22: 0 | Q22: 21.75 | R22: 277.68 | S22: Apple Pay | T22: Direct | U22: Fulfilled | V22: 2024-10-15 | W22: 0 | X22: =TEXT(B22,"MMMM") -> October | Y22: =IF(MONTH(B22)<=3,"Q1",IF(MONTH(B22)<=6,"Q2",IF(MONTH(B22)<=9,"Q3","Q4"))) -> Q4 | Z22: =M22-O22 -> 255.93
A23: #ORD-10022 | B23: 2024-05-07 | C23: 11:37:23 | D23: Amelia Anderson | E23: amelia.anderson85@gmail.com | F23: +1-228-218-5279 | G23: New York | H23: NY | I23: United States | J23: USB-C Fast Charger 65W x3 | K23: Electronics | L23: 1 | M23: 89.97 | N23: SAVE10 | O23: 9 | P23: 0 | Q23: 6.48 | R23: 87.45 | S23: PayPal | T23: Online Store | U23: Refunded | V23: 2024-05-10 | W23: 87.45 | X23: =TEXT(B23,"MMMM") -> May | Y23: =IF(MONTH(B23)<=3,"Q1",IF(MONTH(B23)<=6,"Q2",IF(MONTH(B23)<=9,"Q3","Q4"))) -> Q2 | Z23: =M23-O23 -> 80.97
A24: #ORD-10023 | B24: 2024-06-17 | C24: 18:25:40 | D24: Logan Hill | E24: logan.hill5@gmail.com | F24: +1-201-632-9821 | G24: Dallas | H24: TX | I24: United States | J24: High-Waist Leggings x1 | K24: Apparel | L24: 1 | M24: 42.99 | N24: LOYALTY5 | O24: 2.15 | P24: 4.99 | Q24: 3.47 | R24: 49.3 | S24: Apple Pay | T24: Online Store | U24: Fulfilled | V24: 2024-06-21 | W24: 0 | X24: =TEXT(B24,"MMMM") -> June | Y24: =IF(MONTH(B24)<=3,"Q1",IF(MONTH(B24)<=6,"Q2",IF(MONTH(B24)<=9,"Q3","Q4"))) -> Q2 | Z24: =M24-O24 -> 40.84
A25: #ORD-10024 | B25: 2024-08-30 | C25: 00:13:45 | D25: Charlotte White | E25: charlotte.white9@outlook.com | F25: +1-330-296-7888 | G25: Columbus | H25: OH | I25: United States | J25: Canvas Backpack 25L x1 | K25: Bags & Accessories | L25: 1 | M25: 54.99 | N25: SAVE10 | O25: 5.5 | P25: 7.99 | Q25: 4.95 | R25: 62.43 | S25: Debit Card | T25: Instagram | U25: Fulfilled | V25: 2024-09-04 | W25: 0 | X25: =TEXT(B25,"MMMM") -> August | Y25: =IF(MONTH(B25)<=3,"Q1",IF(MONTH(B25)<=6,"Q2",IF(MONTH(B25)<=9,"Q3","Q4"))) -> Q3 | Z25: =M25-O25 -> 49.49
A26: #ORD-10025 | B26: 2024-07-31 | C26: 19:08:41 | D26: Elizabeth Lopez | E26: elizabeth.lopez73@gmail.com | F26: +1-490-627-6491 | G26: Nashville | H26: TN | I26: United States | J26: Yoga Mat Premium x2 | Running Shoes - Women's x1 | Multivitamin Daily Pack x1 | K26: Sports & Fitness | L26: 3 | M26: 159.96 | N26: SUMMER20 | O26: 31.99 | P26: 0 | Q26: 10.88 | R26: 138.85 | S26: PayPal | T26: Instagram | U26: Fulfilled | V26: 2024-08-01 | W26: 0 | X26: =TEXT(B26,"MMMM") -> July | Y26: =IF(MONTH(B26)<=3,"Q1",IF(MONTH(B26)<=6,"Q2",IF(MONTH(B26)<=9,"Q3","Q4"))) -> Q3 | Z26: =M26-O26 -> 127.97
A27: #ORD-10026 | B27: 2024-03-18 | C27: 08:01:31 | D27: Ethan Thomas | E27: ethan.thomas40@gmail.com | F27: +1-706-509-4997 | G27: El Paso | H27: TX | I27: United States | J27: Portable Bluetooth Speaker x1 | K27: Electronics | L27: 1 | M27: 49.99 | N27: SUMMER20 | O27: 10 | P27: 4.99 | Q27: 3.4 | R27: 48.38 | S27: Debit Card | T27: Facebook | U27: Fulfilled | V27: 2024-03-22 | W27: 0 | X27: =TEXT(B27,"MMMM") -> March | Y27: =IF(MONTH(B27)<=3,"Q1",IF(MONTH(B27)<=6,"Q2",IF(MONTH(B27)<=9,"Q3","Q4"))) -> Q1 | Z27: =M27-O27 -> 39.99
A28: #ORD-10027 | B28: 2024-10-29 | C28: 07:24:14 | D28: James Smith | E28: james.smith97@outlook.com | F28: +1-336-920-8612 | G28: Albuquerque | H28: NM | I28: United States | J28: Running Shoes - Men's x2 | K28: Footwear | L28: 1 | M28: 149.98 | N28: FLASH25 | O28: 37.49 | P28: 0 | Q28: 9.56 | R28: 122.05 | S28: Credit Card | T28: Online Store | U28: Fulfilled | V28: 2024-11-02 | W28: 0 | X28: =TEXT(B28,"MMMM") -> October | Y28: =IF(MONTH(B28)<=3,"Q1",IF(MONTH(B28)<=6,"Q2",IF(MONTH(B28)<=9,"Q3","Q4"))) -> Q4 | Z28: =M28-O28 -> 112.49
A29: #ORD-10028 | B29: 2024-08-25 | C29: 22:20:00 | D29: Owen Torres | E29: owen.torres41@outlook.com | F29: +1-696-741-4919 | G29: Nashville | H29: TN | I29: United States | J29: Leather Wallet Slim x2 | Air Fryer 5.8Qt x1 | Multivitamin Daily Pack x2 | K29: Bags & Accessories | L29: 3 | M29: 179.95 | N29: SUMMER20 | O29: 35.99 | P29: 0 | Q29: 12.24 | R29: 156.2 | S29: Credit Card | T29: Online Store | U29: Fulfilled | V29: 2024-08-30 | W29: 0 | X29: =TEXT(B29,"MMMM") -> August | Y29: =IF(MONTH(B29)<=3,"Q1",IF(MONTH(B29)<=6,"Q2",IF(MONTH(B29)<=9,"Q3","Q4"))) -> Q3 | Z29: =M29-O29 -> 143.96
A30: #ORD-10029 | B30: 2024-04-15 | C30: 12:34:06 | D30: Elijah Robinson | E30: elijah.robinson92@gmail.com | F30: +1-624-517-6421 | G30: Chicago | H30: IL | I30: United States | J30: Leather Wallet Slim x1 | K30: Bags & Accessories | L30: 1 | M30: 29.99 | N30: None | O30: 0 | P30: 5.99 | Q30: 2.1 | R30: 38.08 | S30: Debit Card | T30: Online Store | U30: Fulfilled | V30: 2024-04-16 | W30: 0 | X30: =TEXT(B30,"MMMM") -> April | Y30: =IF(MONTH(B30)<=3,"Q1",IF(MONTH(B30)<=6,"Q2",IF(MONTH(B30)<=9,"Q3","Q4"))) -> Q2 | Z30: =M30-O30 -> 29.99
A31: #ORD-10030 | B31: 2024-06-12 | C31: 04:01:17 | D31: Grace Walker | E31: grace.walker8@gmail.com | F31: +1-629-651-9947 | G31: Columbus | H31: OH | I31: United States | J31: Classic Fit Polo Shirt x1 | K31: Apparel | L31: 1 | M31: 34.99 | N31: None | O31: 0 | P31: 9.99 | Q31: 2.97 | R31: 47.95 | S31: Credit Card | T31: Online Store | U31: Unfulfilled | W31: 0 | X31: =TEXT(B31,"MMMM") -> June | Y31: =IF(MONTH(B31)<=3,"Q1",IF(MONTH(B31)<=6,"Q2",IF(MONTH(B31)<=9,"Q3","Q4"))) -> Q2 | Z31: =M31-O31 -> 34.99
A32: #ORD-10031 | B32: 2024-07-07 | C32: 14:30:41 | D32: Victoria Anderson | E32: victoria.anderson29@gmail.com | F32: +1-603-706-1444 | G32: Indianapolis | H32: IN | I32: United States | J32: Resistance Band Set x1 | K32: Sports & Fitness | L32: 1 | M32: 24.99 | N32: WELCOME15 | O32: 3.75 | P32: 5.99 | Q32: 1.81 | R32: 29.04 | S32: Google Pay | T32: Referral | U32: Refunded | V32: 2024-07-08 | W32: 29.04 | X32: =TEXT(B32,"MMMM") -> July | Y32: =IF(MONTH(B32)<=3,"Q1",IF(MONTH(B32)<=6,"Q2",IF(MONTH(B32)<=9,"Q3","Q4"))) -> Q3 | Z32: =M32-O32 -> 21.24
A33: #ORD-10032 | B33: 2024-04-11 | C33: 00:49:57 | D33: Ethan Lewis | E33: ethan.lewis60@gmail.com | F33: +1-681-119-9837 | G33: Phoenix | H33: AZ | I33: United States | J33: Running Shoes - Women's x1 | K33: Footwear | L33: 1 | M33: 69.99 | N33: SAVE10 | O33: 7 | P33: 9.99 | Q33: 5.04 | R33: 78.02 | S33: Shop Pay | T33: Email Campaign | U33: Fulfilled | V33: 2024-04-12 | W33: 0 | X33: =TEXT(B33,"MMMM") -> April | Y33: =IF(MONTH(B33)<=3,"Q1",IF(MONTH(B33)<=6,"Q2",IF(MONTH(B33)<=9,"Q3","Q4"))) -> Q2 | Z33: =M33-O33 -> 62.99
A34: #ORD-10033 | B34: 2024-09-10 | C34: 02:47:37 | D34: Noah Thompson | E34: noah.thompson84@gmail.com | F34: +1-885-217-4571 | G34: San Diego | H34: CA | I34: United States | J34: Wireless Noise-Cancelling Headphones x3 | K34: Electronics | L34: 1 | M34: 269.97 | N34: None | O34: 0 | P34: 0 | Q34: 16.2 | R34: 286.17 | S34: PayPal | T34: Online Store | U34: Cancelled | W34: 0 | X34: =TEXT(B34,"MMMM") -> September | Y34: =IF(MONTH(B34)<=3,"Q1",IF(MONTH(B34)<=6,"Q2",IF(MONTH(B34)<=9,"Q3","Q4"))) -> Q3 | Z34: =M34-O34 -> 269.97
A35: #ORD-10034 | B35: 2024-08-23 | C35: 19:57:24 | D35: Sebastian Taylor | E35: sebastian.taylor48@gmail.com | F35: +1-913-891-5941 | G35: Memphis | H35: TN | I35: United States | J35: Sunscreen SPF 50 Face x3 | Smart LED Desk Lamp x1 | Classic Fit Polo Shirt x1 | Denim Jacket x1 | Running Shoes - Men's x1 | K35: Beauty | L35: 5 | M35: 271.93 | N35: WELCOME15 | O35: 40.79 | P35: 0 | Q35: 19.65 | R35: 250.79 | S35: Google Pay | T35: Online Store | U35: Fulfilled | V35: 2024-08-24 | W35: 0 | X35: =TEXT(B35,"MMMM") -> August | Y35: =IF(MONTH(B35)<=3,"Q1",IF(MONTH(B35)<=6,"Q2",IF(MONTH(B35)<=9,"Q3","Q4"))) -> Q3 | Z35: =M35-O35 -> 231.14
A36: #ORD-10035 | B36: 2024-06-15 | C36: 08:46:20 | D36: Victoria Davis | E36: victoria.davis73@yahoo.com | F36: +1-924-256-8135 | G36: Louisville | H36: KY | I36: United States | J36: USB-C Fast Charger 65W x1 | Air Fryer 5.8Qt x1 | K36: Electronics | L36: 2 | M36: 109.98 | N36: WELCOME15 | O36: 16.5 | P36: 0 | Q36: 7.95 | R36: 101.43 | S36: Credit Card | T36: TikTok Shop | U36: Cancelled | W36: 0 | X36: =TEXT(B36,"MMMM") -> June | Y36: =IF(MONTH(B36)<=3,"Q1",IF(MONTH(B36)<=6,"Q2",IF(MONTH(B36)<=9,"Q3","Q4"))) -> Q2 | Z36: =M36-O36 -> 93.48
A37: #ORD-10036 | B37: 2024-10-27 | C37: 20:10:53 | D37: Logan Wright | E37: logan.wright35@outlook.com | F37: +1-783-724-7209 | G37: Oklahoma City | H37: OK | I37: United States | J37: Multivitamin Daily Pack x2 | Denim Jacket x1 | K37: Health & Nutrition | L37: 2 | M37: 104.97 | N37: None | O37: 0 | P37: 0 | Q37: 6.3 | R37: 111.27 | S37: Credit Card | T37: Instagram | U37: Cancelled | W37: 0 | X37: =TEXT(B37,"MMMM") -> October | Y37: =IF(MONTH(B37)<=3,"Q1",IF(MONTH(B37)<=6,"Q2",IF(MONTH(B37)<=9,"Q3","Q4"))) -> Q4 | Z37: =M37-O37 -> 104.97
A38: #ORD-10037 | B38: 2024-03-23 | C38: 09:06:01 | D38: Muhammad Johnson | E38: muhammad.johnson42@gmail.com | F38: +1-287-347-7658 | G38: Indianapolis | H38: IN | I38: United States | J38: Hiking Boots x1 | K38: Footwear | L38: 1 | M38: 109.99 | N38: LOYALTY5 | O38: 5.5 | P38: 0 | Q38: 10.45 | R38: 114.94 | S38: Apple Pay | T38: Facebook | U38: Refunded | V38: 2024-03-25 | W38: 114.94 | X38: =TEXT(B38,"MMMM") -> March | Y38: =IF(MONTH(B38)<=3,"Q1",IF(MONTH(B38)<=6,"Q2",IF(MONTH(B38)<=9,"Q3","Q4"))) -> Q1 | Z38: =M38-O38 -> 104.49
A39: #ORD-10038 | B39: 2024-07-09 | C39: 14:47:11 | D39: Michael Torres | E39: michael.torres31@outlook.com | F39: +1-766-643-6632 | G39: Memphis | H39: TN | I39: United States | J39: Wireless Noise-Cancelling Headphones x1 | K39: Electronics | L39: 1 | M39: 89.99 | N39: None | O39: 0 | P39: 0 | Q39: 7.65 | R39: 97.64 | S39: PayPal | T39: Online Store | U39: Partially Fulfilled | V39: 2024-07-13 | W39: 0 | X39: =TEXT(B39,"MMMM") -> July | Y39: =IF(MONTH(B39)<=3,"Q1",IF(MONTH(B39)<=6,"Q2",IF(MONTH(B39)<=9,"Q3","Q4"))) -> Q3 | Z39: =M39-O39 -> 89.99
A40: #ORD-10039 | B40: 2024-04-07 | C40: 15:15:07 | D40: Jack Torres | E40: jack.torres46@yahoo.com | F40: +1-489-202-4180 | G40: Austin | H40: TX | I40: United States | J40: Men's Grooming Kit x1 | K40: Beauty | L40: 1 | M40: 35.99 | N40: None | O40: 0 | P40: 5.99 | Q40: 2.52 | R40: 44.5 | S40: Credit Card | T40: Instagram | U40: Refunded | V40: 2024-04-12 | W40: 44.5 | X40: =TEXT(B40,"MMMM") -> April | Y40: =IF(MONTH(B40)<=3,"Q1",IF(MONTH(B40)<=6,"Q2",IF(MONTH(B40)<=9,"Q3","Q4"))) -> Q2 | Z40: =M40-O40 -> 35.99
A41: #ORD-10040 | B41: 2024-10-01 | C41: 23:12:38 | D41: Evelyn Anderson | E41: evelyn.anderson23@gmail.com | F41: +1-491-580-8843 | G41: Jacksonville | H41: FL | I41: United States | J41: Hiking Boots x3 | Portable Bluetooth Speaker x1 | K41: Footwear | L41: 2 | M41: 379.96 | N41: None | O41: 0 | P41: 0 | Q41: 38 | R41: 417.96 | S41: Apple Pay | T41: Instagram | U41: Fulfilled | V41: 2024-10-06 | W41: 0 | X41: =TEXT(B41,"MMMM") -> October | Y41: =IF(MONTH(B41)<=3,"Q1",IF(MONTH(B41)<=6,"Q2",IF(MONTH(B41)<=9,"Q3","Q4"))) -> Q4 | Z41: =M41-O41 -> 379.96
A42: #ORD-10041 | B42: 2024-11-30 | C42: 15:50:24 | D42: Avery Perez | E42: avery.perez7@gmail.com | F42: +1-454-221-7818 | G42: Philadelphia | H42: PA | I42: United States | J42: Denim Jacket x1 | USB-C Fast Charger 65W x1 | K42: Apparel | L42: 2 | M42: 94.98 | N42: None | O42: 0 | P42: 0 | Q42: 6.65 | R42: 101.63 | S42: Credit Card | T42: Facebook | U42: Fulfilled | V42: 2024-12-01 | W42: 0 | X42: =TEXT(B42,"MMMM") -> November | Y42: =IF(MONTH(B42)<=3,"Q1",IF(MONTH(B42)<=6,"Q2",IF(MONTH(B42)<=9,"Q3","Q4"))) -> Q4 | Z42: =M42-O42 -> 94.98
A43: #ORD-10042 | B43: 2024-07-21 | C43: 22:43:44 | D43: Victoria Flores | E43: victoria.flores80@gmail.com | F43: +1-840-316-5335 | G43: Louisville | H43: KY | I43: United States | J43: Bamboo Sunglasses x1 | K43: Bags & Accessories | L43: 1 | M43: 24.99 | N43: LOYALTY5 | O43: 1.25 | P43: 9.99 | Q43: 1.9 | R43: 35.63 | S43: PayPal | T43: Online Store | U43: Fulfilled | V43: 2024-07-23 | W43: 0 | X43: =TEXT(B43,"MMMM") -> July | Y43: =IF(MONTH(B43)<=3,"Q1",IF(MONTH(B43)<=6,"Q2",IF(MONTH(B43)<=9,"Q3","Q4"))) -> Q3 | Z43: =M43-O43 -> 23.74
A44: #ORD-10043 | B44: 2024-06-07 | C44: 15:39:35 | D44: Ethan Hernandez | E44: ethan.hernandez23@yahoo.com | F44: +1-840-703-4241 | G44: San Diego | H44: CA | I44: United States | J44: Scented Soy Candle Set x1 | Stainless Steel Cookware Set x1 | K44: Home & Living | L44: 2 | M44: 152.98 | N44: SAVE10 | O44: 15.3 | P44: 0 | Q44: 13.77 | R44: 151.45 | S44: Apple Pay | T44: Online Store | U44: Fulfilled | V44: 2024-06-10 | W44: 0 | X44: =TEXT(B44,"MMMM") -> June | Y44: =IF(MONTH(B44)<=3,"Q1",IF(MONTH(B44)<=6,"Q2",IF(MONTH(B44)<=9,"Q3","Q4"))) -> Q2 | Z44: =M44-O44 -> 137.68
A45: #ORD-10044 | B45: 2024-11-17 | C45: 00:45:39 | D45: Jack Davis | E45: jack.davis29@outlook.com | F45: +1-478-612-9847 | G45: Seattle | H45: WA | I45: United States | J45: Portable Bluetooth Speaker x1 | K45: Electronics | L45: 1 | M45: 49.99 | N45: SAVE10 | O45: 5 | P45: 7.99 | Q45: 3.82 | R45: 56.8 | S45: Credit Card | T45: Google Shopping | U45: Unfulfilled | W45: 0 | X45: =TEXT(B45,"MMMM") -> November | Y45: =IF(MONTH(B45)<=3,"Q1",IF(MONTH(B45)<=6,"Q2",IF(MONTH(B45)<=9,"Q3","Q4"))) -> Q4 | Z45: =M45-O45 -> 44.99
A46: #ORD-10045 | B46: 2024-06-16 | C46: 18:47:56 | D46: Michael Robinson | E46: michael.robinson77@gmail.com | F46: +1-241-881-3870 | G46: Chicago | H46: IL | I46: United States | J46: Scented Soy Candle Set x1 | Hiking Boots x3 | Wireless Noise-Cancelling Headphones x2 | K46: Home & Living | L46: 3 | M46: 532.94 | N46: LOYALTY5 | O46: 26.65 | P46: 0 | Q46: 45.57 | R46: 551.86 | S46: Klarna | T46: Referral | U46: Fulfilled | V46: 2024-06-21 | W46: 0 | X46: =TEXT(B46,"MMMM") -> June | Y46: =IF(MONTH(B46)<=3,"Q1",IF(MONTH(B46)<=6,"Q2",IF(MONTH(B46)<=9,"Q3","Q4"))) -> Q2 | Z46: =M46-O46 -> 506.29
A47: #ORD-10046 | B47: 2024-08-15 | C47: 07:40:03 | D47: Ella Wright | E47: ella.wright57@yahoo.com | F47: +1-537-521-9117 | G47: Oklahoma City | H47: OK | I47: United States | J47: Denim Jacket x1 | K47: Apparel | L47: 1 | M47: 64.99 | N47: None | O47: 0 | P47: 9.99 | Q47: 5.2 | R47: 80.18 | S47: Debit Card | T47: Online Store | U47: Fulfilled | V47: 2024-08-17 | W47: 0 | X47: =TEXT(B47,"MMMM") -> August | Y47: =IF(MONTH(B47)<=3,"Q1",IF(MONTH(B47)<=6,"Q2",IF(MONTH(B47)<=9,"Q3","Q4"))) -> Q3 | Z47: =M47-O47 -> 64.99
A48: #ORD-10047 | B48: 2024-05-02 | C48: 03:30:44 | D48: Evelyn Sanchez | E48: evelyn.sanchez98@yahoo.com | F48: +1-623-155-4073 | G48: Baltimore | H48: MD | I48: United States | J48: Smart LED Desk Lamp x3 | K48: Electronics | L48: 1 | M48: 119.97 | N48: WELCOME15 | O48: 18 | P48: 0 | Q48: 9.18 | R48: 111.15 | S48: Shop Pay | T48: Online Store | U48: Refunded | V48: 2024-05-06 | W48: 111.15 | X48: =TEXT(B48,"MMMM") -> May | Y48: =IF(MONTH(B48)<=3,"Q1",IF(MONTH(B48)<=6,"Q2",IF(MONTH(B48)<=9,"Q3","Q4"))) -> Q2 | Z48: =M48-O48 -> 101.97
A49: #ORD-10048 | B49: 2024-06-20 | C49: 16:07:13 | D49: Owen White | E49: owen.white97@gmail.com | F49: +1-518-664-1224 | G49: Nashville | H49: TN | I49: United States | J49: Running Shoes - Women's x1 | Hiking Boots x1 | Coffee Maker Programmable x2 | K49: Footwear | L49: 3 | M49: 289.96 | N49: SUMMER20 | O49: 57.99 | P49: 0 | Q49: 13.92 | R49: 245.89 | S49: Credit Card | T49: Facebook | U49: Fulfilled | V49: 2024-06-22 | W49: 0 | X49: =TEXT(B49,"MMMM") -> June | Y49: =IF(MONTH(B49)<=3,"Q1",IF(MONTH(B49)<=6,"Q2",IF(MONTH(B49)<=9,"Q3","Q4"))) -> Q2 | Z49: =M49-O49 -> 231.97
A50: #ORD-10049 | B50: 2024-06-28 | C50: 05:00:21 | D50: William Clark | E50: william.clark29@outlook.com | F50: +1-395-713-9327 | G50: Chicago | H50: IL | I50: United States | J50: Essential Oil Diffuser x3 | Denim Jacket x1 | Mechanical Keyboard x2 | Stainless Steel Cookware Set x1 | K50: Home & Living | L50: 4 | M50: 533.93 | N50: SUMMER20 | O50: 106.79 | P50: 0 | Q50: 36.31 | R50: 463.45 | S50: Credit Card | T50: Facebook | U50: Unfulfilled | W50: 0 | X50: =TEXT(B50,"MMMM") -> June | Y50: =IF(MONTH(B50)<=3,"Q1",IF(MONTH(B50)<=6,"Q2",IF(MONTH(B50)<=9,"Q3","Q4"))) -> Q2 | Z50: =M50-O50 -> 427.14
A51: #ORD-10050 | B51: 2024-12-28 | C51: 19:49:34 | D51: Isabella Jones | E51: isabella.jones99@yahoo.com | F51: +1-981-656-7180 | G51: Dallas | H51: TX | I51: United States | J51: Hiking Boots x1 | Denim Jacket x1 | Wireless Noise-Cancelling Headphones x1 | K51: Footwear | L51: 3 | M51: 264.97 | N51: SUMMER20 | O51: 52.99 | P51: 0 | Q51: 14.84 | R51: 226.82 | S51: Debit Card | T51: Instagram | U51: Partially Fulfilled | V51: 2025-01-02 | W51: 0 | X51: =TEXT(B51,"MMMM") -> December | Y51: =IF(MONTH(B51)<=3,"Q1",IF(MONTH(B51)<=6,"Q2",IF(MONTH(B51)<=9,"Q3","Q4"))) -> Q4 | Z51: =M51-O51 -> 211.98
A52: #ORD-10051 | B52: 2024-05-28 | C52: 17:32:49 | D52: Sebastian Lee | E52: sebastian.lee25@yahoo.com | F52: +1-237-229-9229 | G52: Milwaukee | H52: WI | I52: United States | J52: Classic Fit Polo Shirt x1 | K52: Apparel | L52: 1 | M52: 34.99 | N52: SAVE10 | O52: 3.5 | P52: 9.99 | Q52: 3.15 | R52: 44.63 | S52: Google Pay | T52: Online Store | U52: Fulfilled | V52: 2024-06-01 | W52: 0 | X52: =TEXT(B52,"MMMM") -> May | Y52: =IF(MONTH(B52)<=3,"Q1",IF(MONTH(B52)<=6,"Q2",IF(MONTH(B52)<=9,"Q3","Q4"))) -> Q2 | Z52: =M52-O52 -> 31.49
A53: #ORD-10052 | B53: 2024-07-23 | C53: 06:13:09 | D53: Daniel Perez | E53: daniel.perez13@yahoo.com | F53: +1-890-979-9742 | G53: Milwaukee | H53: WI | I53: United States | J53: Wireless Noise-Cancelling Headphones x2 | Men's Grooming Kit x3 | Mechanical Keyboard x1 | Multivitamin Daily Pack x2 | K53: Electronics | L53: 4 | M53: 447.92 | N53: SAVE10 | O53: 44.79 | P53: 0 | Q53: 32.25 | R53: 435.38 | S53: PayPal | T53: Online Store | U53: Fulfilled | V53: 2024-07-26 | W53: 0 | X53: =TEXT(B53,"MMMM") -> July | Y53: =IF(MONTH(B53)<=3,"Q1",IF(MONTH(B53)<=6,"Q2",IF(MONTH(B53)<=9,"Q3","Q4"))) -> Q3 | Z53: =M53-O53 -> 403.13
A54: #ORD-10053 | B54: 2024-07-29 | C54: 02:38:05 | D54: Elizabeth Lee | E54: elizabeth.lee92@yahoo.com | F54: +1-370-810-5906 | G54: Oklahoma City | H54: OK | I54: United States | J54: USB-C Fast Charger 65W x1 | K54: Electronics | L54: 1 | M54: 29.99 | N54: SAVE10 | O54: 3 | P54: 5.99 | Q54: 2.7 | R54: 35.68 | S54: Credit Card | T54: Referral | U54: Fulfilled | V54: 2024-08-02 | W54: 0 | X54: =TEXT(B54,"MMMM") -> July | Y54: =IF(MONTH(B54)<=3,"Q1",IF(MONTH(B54)<=6,"Q2",IF(MONTH(B54)<=9,"Q3","Q4"))) -> Q3 | Z54: =M54-O54 -> 26.99
A55: #ORD-10054 | B55: 2024-05-25 | C55: 13:46:19 | D55: Liam Williams | E55: liam.williams8@gmail.com | F55: +1-834-799-4945 | G55: Austin | H55: TX | I55: United States | J55: Casual Sneakers x1 | K55: Footwear | L55: 1 | M55: 59.99 | N55: LOYALTY5 | O55: 3 | P55: 5.99 | Q55: 3.99 | R55: 66.97 | S55: Credit Card | T55: Facebook | U55: Unfulfilled | W55: 0 | X55: =TEXT(B55,"MMMM") -> May | Y55: =IF(MONTH(B55)<=3,"Q1",IF(MONTH(B55)<=6,"Q2",IF(MONTH(B55)<=9,"Q3","Q4"))) -> Q2 | Z55: =M55-O55 -> 56.99
A56: #ORD-10055 | B56: 2024-04-08 | C56: 15:14:25 | D56: Michael Hill | E56: michael.hill30@gmail.com | F56: +1-506-754-7951 | G56: Phoenix | H56: AZ | I56: United States | J56: Anti-Aging Serum 1oz x2 | Wireless Noise-Cancelling Headphones x1 | K56: Beauty | L56: 2 | M56: 189.97 | N56: SAVE10 | O56: 19 | P56: 0 | Q56: 17.1 | R56: 188.07 | S56: Debit Card | T56: Online Store | U56: Partially Fulfilled | V56: 2024-04-13 | W56: 0 | X56: =TEXT(B56,"MMMM") -> April | Y56: =IF(MONTH(B56)<=3,"Q1",IF(MONTH(B56)<=6,"Q2",IF(MONTH(B56)<=9,"Q3","Q4"))) -> Q2 | Z56: =M56-O56 -> 170.97
A57: #ORD-10056 | B57: 2024-05-29 | C57: 09:36:03 | D57: Harper Walker | E57: harper.walker39@gmail.com | F57: +1-779-985-1803 | G57: Milwaukee | H57: WI | I57: United States | J57: Smart LED Desk Lamp x1 | Casual Sneakers x1 | Protein Powder Chocolate 2lb x3 | K57: Electronics | L57: 3 | M57: 234.95 | N57: SAVE10 | O57: 23.5 | P57: 0 | Q57: 12.69 | R57: 224.14 | S57: Klarna | T57: Facebook | U57: Fulfilled | V57: 2024-05-30 | W57: 0 | X57: =TEXT(B57,"MMMM") -> May | Y57: =IF(MONTH(B57)<=3,"Q1",IF(MONTH(B57)<=6,"Q2",IF(MONTH(B57)<=9,"Q3","Q4"))) -> Q2 | Z57: =M57-O57 -> 211.45
A58: #ORD-10057 | B58: 2024-11-07 | C58: 10:32:51 | D58: Victoria Allen | E58: victoria.allen37@yahoo.com | F58: +1-651-134-6977 | G58: Baltimore | H58: MD | I58: United States | J58: Essential Oil Diffuser x1 | K58: Home & Living | L58: 1 | M58: 32.99 | N58: SAVE10 | O58: 3.3 | P58: 5.99 | Q58: 2.97 | R58: 38.65 | S58: Credit Card | T58: Facebook | U58: Fulfilled | V58: 2024-11-10 | W58: 0 | X58: =TEXT(B58,"MMMM") -> November | Y58: =IF(MONTH(B58)<=3,"Q1",IF(MONTH(B58)<=6,"Q2",IF(MONTH(B58)<=9,"Q3","Q4"))) -> Q4 | Z58: =M58-O58 -> 29.69
A59: #ORD-10058 | B59: 2024-06-10 | C59: 08:46:10 | D59: Isabella Garcia | E59: isabella.garcia38@gmail.com | F59: +1-693-925-5835 | G59: Tucson | H59: AZ | I59: United States | J59: Mechanical Keyboard x2 | K59: Electronics | L59: 1 | M59: 239.98 | N59: SAVE10 | O59: 24 | P59: 0 | Q59: 19.44 | R59: 235.42 | S59: Debit Card | T59: Online Store | U59: Fulfilled | V59: 2024-06-13 | W59: 0 | X59: =TEXT(B59,"MMMM") -> June | Y59: =IF(MONTH(B59)<=3,"Q1",IF(MONTH(B59)<=6,"Q2",IF(MONTH(B59)<=9,"Q3","Q4"))) -> Q2 | Z59: =M59-O59 -> 215.98
A60: #ORD-10059 | B60: 2024-03-28 | C60: 14:52:52 | D60: Muhammad Davis | E60: muhammad.davis10@gmail.com | F60: +1-798-490-7086 | G60: Charlotte | H60: NC | I60: United States | J60: Men's Grooming Kit x3 | Anti-Aging Serum 1oz x2 | Protein Powder Chocolate 2lb x1 | K60: Beauty | L60: 3 | M60: 252.94 | N60: WELCOME15 | O60: 37.94 | P60: 0 | Q60: 12.9 | R60: 227.9 | S60: Credit Card | T60: Online Store | U60: Partially Fulfilled | V60: 2024-03-31 | W60: 0 | X60: =TEXT(B60,"MMMM") -> March | Y60: =IF(MONTH(B60)<=3,"Q1",IF(MONTH(B60)<=6,"Q2",IF(MONTH(B60)<=9,"Q3","Q4"))) -> Q1 | Z60: =M60-O60 -> 215
A61: #ORD-10060 | B61: 2024-05-07 | C61: 09:14:24 | D61: Sophia Anderson | E61: sophia.anderson4@outlook.com | F61: +1-750-238-7367 | G61: Indianapolis | H61: IN | I61: United States | J61: Casual Sneakers x1 | Essential Oil Diffuser x2 | USB-C Fast Charger 65W x1 | Denim Jacket x1 | K61: Footwear | L61: 4 | M61: 220.95 | N61: None | O61: 0 | P61: 0 | Q61: 13.26 | R61: 234.21 | S61: Credit Card | T61: Instagram | U61: Fulfilled | V61: 2024-05-09 | W61: 0 | X61: =TEXT(B61,"MMMM") -> May | Y61: =IF(MONTH(B61)<=3,"Q1",IF(MONTH(B61)<=6,"Q2",IF(MONTH(B61)<=9,"Q3","Q4"))) -> Q2 | Z61: =M61-O61 -> 220.95
A62: #ORD-10061 | B62: 2024-08-16 | C62: 02:24:31 | D62: Sebastian White | E62: sebastian.white96@outlook.com | F62: +1-441-975-6942 | G62: El Paso | H62: TX | I62: United States | J62: Mechanical Keyboard x1 | Leather Wallet Slim x2 | Multivitamin Daily Pack x1 | K62: Electronics | L62: 3 | M62: 199.96 | N62: SAVE10 | O62: 20 | P62: 0 | Q62: 10.8 | R62: 190.76 | S62: PayPal | T62: Online Store | U62: Cancelled | W62: 0 | X62: =TEXT(B62,"MMMM") -> August | Y62: =IF(MONTH(B62)<=3,"Q1",IF(MONTH(B62)<=6,"Q2",IF(MONTH(B62)<=9,"Q3","Q4"))) -> Q3 | Z62: =M62-O62 -> 179.96
A63: #ORD-10062 | B63: 2024-06-03 | C63: 14:55:49 | D63: Sophia White | E63: sophia.white83@gmail.com | F63: +1-541-349-3063 | G63: Seattle | H63: WA | I63: United States | J63: Smart LED Desk Lamp x3 | K63: Electronics | L63: 1 | M63: 119.97 | N63: SUMMER20 | O63: 23.99 | P63: 0 | Q63: 5.76 | R63: 101.74 | S63: PayPal | T63: Facebook | U63: Fulfilled | V63: 2024-06-04 | W63: 0 | X63: =TEXT(B63,"MMMM") -> June | Y63: =IF(MONTH(B63)<=3,"Q1",IF(MONTH(B63)<=6,"Q2",IF(MONTH(B63)<=9,"Q3","Q4"))) -> Q2 | Z63: =M63-O63 -> 95.98
A64: #ORD-10063 | B64: 2024-11-11 | C64: 18:12:10 | D64: Chloe Wilson | E64: chloe.wilson98@outlook.com | F64: +1-334-115-6869 | G64: Chicago | H64: IL | I64: United States | J64: Resistance Band Set x2 | Classic Fit Polo Shirt x1 | Mechanical Keyboard x1 | K64: Sports & Fitness | L64: 3 | M64: 204.96 | N64: None | O64: 0 | P64: 0 | Q64: 14.35 | R64: 219.31 | S64: Debit Card | T64: Email Campaign | U64: Fulfilled | V64: 2024-11-12 | W64: 0 | X64: =TEXT(B64,"MMMM") -> November | Y64: =IF(MONTH(B64)<=3,"Q1",IF(MONTH(B64)<=6,"Q2",IF(MONTH(B64)<=9,"Q3","Q4"))) -> Q4 | Z64: =M64-O64 -> 204.96
A65: #ORD-10064 | B65: 2024-01-21 | C65: 08:23:39 | D65: Oliver Hill | E65: oliver.hill3@gmail.com | F65: +1-715-326-1710 | G65: Austin | H65: TX | I65: United States | J65: Multivitamin Daily Pack x1 | K65: Health & Nutrition | L65: 1 | M65: 19.99 | N65: None | O65: 0 | P65: 9.99 | Q65: 1.7 | R65: 31.68 | S65: Shop Pay | T65: Instagram | U65: Fulfilled | V65: 2024-01-25 | W65: 0 | X65: =TEXT(B65,"MMMM") -> January | Y65: =IF(MONTH(B65)<=3,"Q1",IF(MONTH(B65)<=6,"Q2",IF(MONTH(B65)<=9,"Q3","Q4"))) -> Q1 | Z65: =M65-O65 -> 19.99
A66: #ORD-10065 | B66: 2024-07-05 | C66: 00:26:05 | D66: Owen Martin | E66: owen.martin83@yahoo.com | F66: +1-848-699-9984 | G66: Charlotte | H66: NC | I66: United States | J66: Multivitamin Daily Pack x1 | Anti-Aging Serum 1oz x2 | Smart LED Desk Lamp x1 | K66: Health & Nutrition | L66: 3 | M66: 159.96 | N66: None | O66: 0 | P66: 0 | Q66: 12.8 | R66: 172.76 | S66: PayPal | T66: Online Store | U66: Fulfilled | V66: 2024-07-10 | W66: 0 | X66: =TEXT(B66,"MMMM") -> July | Y66: =IF(MONTH(B66)<=3,"Q1",IF(MONTH(B66)<=6,"Q2",IF(MONTH(B66)<=9,"Q3","Q4"))) -> Q3 | Z66: =M66-O66 -> 159.96
A67: #ORD-10066 | B67: 2024-07-15 | C67: 08:04:39 | D67: Abigail Harris | E67: abigail.harris68@gmail.com | F67: +1-547-947-8430 | G67: Nashville | H67: TN | I67: United States | J67: Smart LED Desk Lamp x2 | High-Waist Leggings x2 | K67: Electronics | L67: 2 | M67: 165.96 | N67: FLASH25 | O67: 41.49 | P67: 0 | Q67: 12.45 | R67: 136.92 | S67: Apple Pay | T67: Instagram | U67: Fulfilled | V67: 2024-07-19 | W67: 0 | X67: =TEXT(B67,"MMMM") -> July | Y67: =IF(MONTH(B67)<=3,"Q1",IF(MONTH(B67)<=6,"Q2",IF(MONTH(B67)<=9,"Q3","Q4"))) -> Q3 | Z67: =M67-O67 -> 124.47
A68: #ORD-10067 | B68: 2024-05-01 | C68: 08:55:50 | D68: Henry Clark | E68: henry.clark13@gmail.com | F68: +1-769-161-6400 | G68: Portland | H68: OR | I68: United States | J68: Insulated Water Bottle 32oz x1 | Mechanical Keyboard x1 | K68: Sports & Fitness | L68: 2 | M68: 147.98 | N68: None | O68: 0 | P68: 0 | Q68: 8.88 | R68: 156.86 | S68: Credit Card | T68: Online Store | U68: Partially Fulfilled | V68: 2024-05-03 | W68: 0 | X68: =TEXT(B68,"MMMM") -> May | Y68: =IF(MONTH(B68)<=3,"Q1",IF(MONTH(B68)<=6,"Q2",IF(MONTH(B68)<=9,"Q3","Q4"))) -> Q2 | Z68: =M68-O68 -> 147.98
A69: #ORD-10068 | B69: 2024-12-21 | C69: 16:16:54 | D69: Mason Clark | E69: mason.clark86@yahoo.com | F69: +1-769-476-2882 | G69: Jacksonville | H69: FL | I69: United States | J69: Yoga Mat Premium x1 | Scented Soy Candle Set x1 | K69: Sports & Fitness | L69: 2 | M69: 57.98 | N69: FLASH25 | O69: 14.5 | P69: 5.99 | Q69: 3.04 | R69: 52.51 | S69: PayPal | T69: Online Store | U69: Fulfilled | V69: 2024-12-24 | W69: 0 | X69: =TEXT(B69,"MMMM") -> December | Y69: =IF(MONTH(B69)<=3,"Q1",IF(MONTH(B69)<=6,"Q2",IF(MONTH(B69)<=9,"Q3","Q4"))) -> Q4 | Z69: =M69-O69 -> 43.48
A70: #ORD-10069 | B70: 2024-11-13 | C70: 20:17:28 | D70: Elijah Nguyen | E70: elijah.nguyen55@outlook.com | F70: +1-559-106-3972 | G70: San Diego | H70: CA | I70: United States | J70: Anti-Aging Serum 1oz x1 | Essential Oil Diffuser x1 | K70: Beauty | L70: 2 | M70: 82.98 | N70: SAVE10 | O70: 8.3 | P70: 0 | Q70: 4.48 | R70: 79.16 | S70: Credit Card | T70: Google Shopping | U70: Fulfilled | V70: 2024-11-16 | W70: 0 | X70: =TEXT(B70,"MMMM") -> November | Y70: =IF(MONTH(B70)<=3,"Q1",IF(MONTH(B70)<=6,"Q2",IF(MONTH(B70)<=9,"Q3","Q4"))) -> Q4 | Z70: =M70-O70 -> 74.68
A71: #ORD-10070 | B71: 2024-10-14 | C71: 18:19:55 | D71: James Nguyen | E71: james.nguyen52@gmail.com | F71: +1-810-186-1861 | G71: El Paso | H71: TX | I71: United States | J71: Wireless Noise-Cancelling Headphones x2 | USB-C Fast Charger 65W x1 | K71: Electronics | L71: 2 | M71: 209.97 | N71: WELCOME15 | O71: 31.5 | P71: 0 | Q71: 15.17 | R71: 193.64 | S71: Credit Card | T71: Online Store | U71: Partially Fulfilled | V71: 2024-10-19 | W71: 0 | X71: =TEXT(B71,"MMMM") -> October | Y71: =IF(MONTH(B71)<=3,"Q1",IF(MONTH(B71)<=6,"Q2",IF(MONTH(B71)<=9,"Q3","Q4"))) -> Q4 | Z71: =M71-O71 -> 178.47
A72: #ORD-10071 | B72: 2024-02-01 | C72: 16:23:41 | D72: James Hernandez | E72: james.hernandez80@gmail.com | F72: +1-640-213-5640 | G72: Memphis | H72: TN | I72: United States | J72: Anti-Aging Serum 1oz x1 | K72: Beauty | L72: 1 | M72: 49.99 | N72: LOYALTY5 | O72: 2.5 | P72: 9.99 | Q72: 4.04 | R72: 61.52 | S72: Credit Card | T72: Google Shopping | U72: Fulfilled | V72: 2024-02-04 | W72: 0 | X72: =TEXT(B72,"MMMM") -> February | Y72: =IF(MONTH(B72)<=3,"Q1",IF(MONTH(B72)<=6,"Q2",IF(MONTH(B72)<=9,"Q3","Q4"))) -> Q1 | Z72: =M72-O72 -> 47.49
A73: #ORD-10072 | B73: 2024-03-26 | C73: 15:22:50 | D73: Daniel Allen | E73: daniel.allen86@gmail.com | F73: +1-322-107-9149 | G73: San Francisco | H73: CA | I73: United States | J73: Scented Soy Candle Set x1 | K73: Home & Living | L73: 1 | M73: 22.99 | N73: None | O73: 0 | P73: 7.99 | Q73: 1.61 | R73: 32.59 | S73: Shop Pay | T73: Google Shopping | U73: Fulfilled | V73: 2024-03-29 | W73: 0 | X73: =TEXT(B73,"MMMM") -> March | Y73: =IF(MONTH(B73)<=3,"Q1",IF(MONTH(B73)<=6,"Q2",IF(MONTH(B73)<=9,"Q3","Q4"))) -> Q1 | Z73: =M73-O73 -> 22.99
A74: #ORD-10073 | B74: 2024-08-04 | C74: 23:40:51 | D74: Jack Lopez | E74: jack.lopez49@yahoo.com | F74: +1-926-755-7843 | G74: Phoenix | H74: AZ | I74: United States | J74: High-Waist Leggings x1 | Insulated Water Bottle 32oz x2 | USB-C Fast Charger 65W x1 | K74: Apparel | L74: 3 | M74: 128.96 | N74: SUMMER20 | O74: 25.79 | P74: 0 | Q74: 6.19 | R74: 109.36 | S74: Apple Pay | T74: Facebook | U74: Unfulfilled | W74: 0 | X74: =TEXT(B74,"MMMM") -> August | Y74: =IF(MONTH(B74)<=3,"Q1",IF(MONTH(B74)<=6,"Q2",IF(MONTH(B74)<=9,"Q3","Q4"))) -> Q3 | Z74: =M74-O74 -> 103.17
A75: #ORD-10074 | B75: 2024-08-28 | C75: 01:20:42 | D75: Evelyn Davis | E75: evelyn.davis3@yahoo.com | F75: +1-517-863-6562 | G75: Fort Worth | H75: TX | I75: United States | J75: Sunscreen SPF 50 Face x1 | Bamboo Sunglasses x1 | K75: Beauty | L75: 2 | M75: 43.98 | N75: None | O75: 0 | P75: 5.99 | Q75: 3.74 | R75: 53.71 | S75: PayPal | T75: Instagram | U75: Unfulfilled | W75: 0 | X75: =TEXT(B75,"MMMM") -> August | Y75: =IF(MONTH(B75)<=3,"Q1",IF(MONTH(B75)<=6,"Q2",IF(MONTH(B75)<=9,"Q3","Q4"))) -> Q3 | Z75: =M75-O75 -> 43.98
A76: #ORD-10075 | B76: 2024-09-02 | C76: 22:04:54 | D76: Amelia Perez | E76: amelia.perez22@gmail.com | F76: +1-305-249-5193 | G76: Memphis | H76: TN | I76: United States | J76: Air Fryer 5.8Qt x1 | K76: Kitchen | L76: 1 | M76: 79.99 | N76: SAVE10 | O76: 8 | P76: 0 | Q76: 5.76 | R76: 77.75 | S76: PayPal | T76: Email Campaign | U76: Fulfilled | V76: 2024-09-04 | W76: 0 | X76: =TEXT(B76,"MMMM") -> September | Y76: =IF(MONTH(B76)<=3,"Q1",IF(MONTH(B76)<=6,"Q2",IF(MONTH(B76)<=9,"Q3","Q4"))) -> Q3 | Z76: =M76-O76 -> 71.99
A77: #ORD-10076 | B77: 2024-03-09 | C77: 19:07:17 | D77: Charlotte Lopez | E77: charlotte.lopez20@outlook.com | F77: +1-269-580-8245 | G77: Nashville | H77: TN | I77: United States | J77: Essential Oil Diffuser x1 | Stainless Steel Cookware Set x1 | Organic Green Tea 100ct x1 | Classic Fit Polo Shirt x2 | K77: Home & Living | L77: 4 | M77: 247.95 | N77: LOYALTY5 | O77: 12.4 | P77: 0 | Q77: 18.84 | R77: 254.39 | S77: Apple Pay | T77: Facebook | U77: Fulfilled | V77: 2024-03-13 | W77: 0 | X77: =TEXT(B77,"MMMM") -> March | Y77: =IF(MONTH(B77)<=3,"Q1",IF(MONTH(B77)<=6,"Q2",IF(MONTH(B77)<=9,"Q3","Q4"))) -> Q1 | Z77: =M77-O77 -> 235.55
A78: #ORD-10077 | B78: 2024-01-29 | C78: 19:30:25 | D78: Aiden Moore | E78: aiden.moore8@gmail.com | F78: +1-808-619-7299 | G78: Denver | H78: CO | I78: United States | J78: Organic Green Tea 100ct x1 | K78: Food & Beverage | L78: 1 | M78: 14.99 | N78: SAVE10 | O78: 1.5 | P78: 7.99 | Q78: 0.81 | R78: 22.29 | S78: PayPal | T78: Referral | U78: Fulfilled | V78: 2024-02-03 | W78: 0 | X78: =TEXT(B78,"MMMM") -> January | Y78: =IF(MONTH(B78)<=3,"Q1",IF(MONTH(B78)<=6,"Q2",IF(MONTH(B78)<=9,"Q3","Q4"))) -> Q1 | Z78: =M78-O78 -> 13.49
A79: #ORD-10078 | B79: 2024-11-10 | C79: 12:01:53 | D79: Sebastian Hill | E79: sebastian.hill95@yahoo.com | F79: +1-716-761-3827 | G79: Seattle | H79: WA | I79: United States | J79: Running Shoes - Women's x1 | Resistance Band Set x1 | K79: Footwear | L79: 2 | M79: 94.98 | N79: None | O79: 0 | P79: 0 | Q79: 8.07 | R79: 103.05 | S79: Credit Card | T79: Direct | U79: Partially Fulfilled | V79: 2024-11-11 | W79: 0 | X79: =TEXT(B79,"MMMM") -> November | Y79: =IF(MONTH(B79)<=3,"Q1",IF(MONTH(B79)<=6,"Q2",IF(MONTH(B79)<=9,"Q3","Q4"))) -> Q4 | Z79: =M79-O79 -> 94.98
A80: #ORD-10079 | B80: 2024-08-24 | C80: 19:47:54 | D80: Olivia Thomas | E80: olivia.thomas57@outlook.com | F80: +1-537-196-7333 | G80: Boston | H80: MA | I80: United States | J80: Insulated Water Bottle 32oz x2 | K80: Sports & Fitness | L80: 1 | M80: 55.98 | N80: WELCOME15 | O80: 8.4 | P80: 9.99 | Q80: 3.81 | R80: 61.38 | S80: PayPal | T80: Online Store | U80: Partially Fulfilled | V80: 2024-08-25 | W80: 0 | X80: =TEXT(B80,"MMMM") -> August | Y80: =IF(MONTH(B80)<=3,"Q1",IF(MONTH(B80)<=6,"Q2",IF(MONTH(B80)<=9,"Q3","Q4"))) -> Q3 | Z80: =M80-O80 -> 47.58
A81: #ORD-10080 | B81: 2024-02-28 | C81: 09:34:51 | D81: Evelyn Taylor | E81: evelyn.taylor85@outlook.com | F81: +1-772-485-6381 | G81: Portland | H81: OR | I81: United States | J81: Linen Throw Blanket x1 | K81: Home & Living | L81: 1 | M81: 39.99 | N81: SAVE10 | O81: 4 | P81: 7.99 | Q81: 3.6 | R81: 47.58 | S81: PayPal | T81: Online Store | U81: Fulfilled | V81: 2024-03-02 | W81: 0 | X81: =TEXT(B81,"MMMM") -> February | Y81: =IF(MONTH(B81)<=3,"Q1",IF(MONTH(B81)<=6,"Q2",IF(MONTH(B81)<=9,"Q3","Q4"))) -> Q1 | Z81: =M81-O81 -> 35.99
A82: #ORD-10081 | B82: 2024-01-08 | C82: 01:55:15 | D82: Isabella Wright | E82: isabella.wright83@outlook.com | F82: +1-502-964-2657 | G82: Chicago | H82: IL | I82: United States | J82: Running Shoes - Men's x3 | K82: Footwear | L82: 1 | M82: 224.97 | N82: SAVE10 | O82: 22.5 | P82: 0 | Q82: 17.21 | R82: 219.68 | S82: Credit Card | T82: Referral | U82: Fulfilled | V82: 2024-01-09 | W82: 0 | X82: =TEXT(B82,"MMMM") -> January | Y82: =IF(MONTH(B82)<=3,"Q1",IF(MONTH(B82)<=6,"Q2",IF(MONTH(B82)<=9,"Q3","Q4"))) -> Q1 | Z82: =M82-O82 -> 202.47
A83: #ORD-10082 | B83: 2024-05-10 | C83: 18:52:17 | D83: Scarlett Scott | E83: scarlett.scott95@yahoo.com | F83: +1-654-725-5668 | G83: Baltimore | H83: MD | I83: United States | J83: Scented Soy Candle Set x1 | Mechanical Keyboard x1 | Protein Powder Chocolate 2lb x1 | K83: Home & Living | L83: 3 | M83: 187.97 | N83: LOYALTY5 | O83: 9.4 | P83: 0 | Q83: 12.5 | R83: 191.07 | S83: PayPal | T83: Online Store | U83: Partially Fulfilled | V83: 2024-05-12 | W83: 0 | X83: =TEXT(B83,"MMMM") -> May | Y83: =IF(MONTH(B83)<=3,"Q1",IF(MONTH(B83)<=6,"Q2",IF(MONTH(B83)<=9,"Q3","Q4"))) -> Q2 | Z83: =M83-O83 -> 178.57
A84: #ORD-10083 | B84: 2024-11-10 | C84: 00:55:14 | D84: Avery Anderson | E84: avery.anderson31@gmail.com | F84: +1-365-936-4271 | G84: Seattle | H84: WA | I84: United States | J84: Leather Wallet Slim x1 | Denim Jacket x3 | Running Shoes - Women's x3 | K84: Bags & Accessories | L84: 3 | M84: 434.93 | N84: SUMMER20 | O84: 86.99 | P84: 0 | Q84: 27.84 | R84: 375.78 | S84: Shop Pay | T84: Instagram | U84: Unfulfilled | W84: 0 | X84: =TEXT(B84,"MMMM") -> November | Y84: =IF(MONTH(B84)<=3,"Q1",IF(MONTH(B84)<=6,"Q2",IF(MONTH(B84)<=9,"Q3","Q4"))) -> Q4 | Z84: =M84-O84 -> 347.94
A85: #ORD-10084 | B85: 2024-07-05 | C85: 15:25:46 | D85: Victoria Rodriguez | E85: victoria.rodriguez33@gmail.com | F85: +1-293-327-8391 | G85: Milwaukee | H85: WI | I85: United States | J85: Coffee Maker Programmable x2 | Bamboo Sunglasses x1 | Smart LED Desk Lamp x1 | K85: Kitchen | L85: 3 | M85: 174.96 | N85: None | O85: 0 | P85: 0 | Q85: 12.25 | R85: 187.21 | S85: Credit Card | T85: Direct | U85: Fulfilled | V85: 2024-07-09 | W85: 0 | X85: =TEXT(B85,"MMMM") -> July | Y85: =IF(MONTH(B85)<=3,"Q1",IF(MONTH(B85)<=6,"Q2",IF(MONTH(B85)<=9,"Q3","Q4"))) -> Q3 | Z85: =M85-O85 -> 174.96
A86: #ORD-10085 | B86: 2024-05-25 | C86: 05:34:25 | D86: Emily Johnson | E86: emily.johnson7@gmail.com | F86: +1-239-393-8740 | G86: Columbus | H86: OH | I86: United States | J86: USB-C Fast Charger 65W x1 | K86: Electronics | L86: 1 | M86: 29.99 | N86: None | O86: 0 | P86: 7.99 | Q86: 1.8 | R86: 39.78 | S86: Apple Pay | T86: Facebook | U86: Fulfilled | V86: 2024-05-27 | W86: 0 | X86: =TEXT(B86,"MMMM") -> May | Y86: =IF(MONTH(B86)<=3,"Q1",IF(MONTH(B86)<=6,"Q2",IF(MONTH(B86)<=9,"Q3","Q4"))) -> Q2 | Z86: =M86-O86 -> 29.99
A87: #ORD-10086 | B87: 2024-01-31 | C87: 18:26:15 | D87: Isabella Young | E87: isabella.young79@gmail.com | F87: +1-508-224-1782 | G87: Charlotte | H87: NC | I87: United States | J87: Running Shoes - Women's x2 | K87: Footwear | L87: 1 | M87: 139.98 | N87: FLASH25 | O87: 34.99 | P87: 0 | Q87: 10.5 | R87: 115.49 | S87: PayPal | T87: Instagram | U87: Fulfilled | V87: 2024-02-02 | W87: 0 | X87: =TEXT(B87,"MMMM") -> January | Y87: =IF(MONTH(B87)<=3,"Q1",IF(MONTH(B87)<=6,"Q2",IF(MONTH(B87)<=9,"Q3","Q4"))) -> Q1 | Z87: =M87-O87 -> 104.99
A88: #ORD-10087 | B88: 2024-02-13 | C88: 01:16:13 | D88: Oliver Clark | E88: oliver.clark80@gmail.com | F88: +1-626-291-2402 | G88: Oklahoma City | H88: OK | I88: United States | J88: Stainless Steel Cookware Set x1 | Scented Soy Candle Set x1 | Coffee Maker Programmable x1 | K88: Kitchen | L88: 3 | M88: 207.97 | N88: None | O88: 0 | P88: 0 | Q88: 16.64 | R88: 224.61 | S88: Debit Card | T88: Facebook | U88: Fulfilled | V88: 2024-02-18 | W88: 0 | X88: =TEXT(B88,"MMMM") -> February | Y88: =IF(MONTH(B88)<=3,"Q1",IF(MONTH(B88)<=6,"Q2",IF(MONTH(B88)<=9,"Q3","Q4"))) -> Q1 | Z88: =M88-O88 -> 207.97
A89: #ORD-10088 | B89: 2024-07-16 | C89: 03:23:07 | D89: Owen White | E89: owen.white68@outlook.com | F89: +1-446-850-2698 | G89: Chicago | H89: IL | I89: United States | J89: Protein Powder Chocolate 2lb x1 | Canvas Backpack 25L x1 | K89: Health & Nutrition | L89: 2 | M89: 99.98 | N89: SAVE10 | O89: 10 | P89: 0 | Q89: 7.2 | R89: 97.18 | S89: Shop Pay | T89: Online Store | U89: Fulfilled | V89: 2024-07-19 | W89: 0 | X89: =TEXT(B89,"MMMM") -> July | Y89: =IF(MONTH(B89)<=3,"Q1",IF(MONTH(B89)<=6,"Q2",IF(MONTH(B89)<=9,"Q3","Q4"))) -> Q3 | Z89: =M89-O89 -> 89.98
A90: #ORD-10089 | B90: 2024-05-11 | C90: 11:29:20 | D90: Daniel Perez | E90: daniel.perez6@gmail.com | F90: +1-237-400-4302 | G90: Phoenix | H90: AZ | I90: United States | J90: Running Shoes - Men's x1 | Denim Jacket x3 | Classic Fit Polo Shirt x1 | K90: Footwear | L90: 3 | M90: 304.95 | N90: None | O90: 0 | P90: 0 | Q90: 21.35 | R90: 326.3 | S90: Credit Card | T90: Email Campaign | U90: Cancelled | W90: 0 | X90: =TEXT(B90,"MMMM") -> May | Y90: =IF(MONTH(B90)<=3,"Q1",IF(MONTH(B90)<=6,"Q2",IF(MONTH(B90)<=9,"Q3","Q4"))) -> Q2 | Z90: =M90-O90 -> 304.95
A91: #ORD-10090 | B91: 2024-04-30 | C91: 10:07:00 | D91: Olivia Gonzalez | E91: olivia.gonzalez6@gmail.com | F91: +1-327-918-7029 | G91: Albuquerque | H91: NM | I91: United States | J91: Denim Jacket x1 | Coffee Maker Programmable x1 | K91: Apparel | L91: 2 | M91: 119.98 | N91: None | O91: 0 | P91: 0 | Q91: 9.6 | R91: 129.58 | S91: Debit Card | T91: Email Campaign | U91: Partially Fulfilled | V91: 2024-05-03 | W91: 0 | X91: =TEXT(B91,"MMMM") -> April | Y91: =IF(MONTH(B91)<=3,"Q1",IF(MONTH(B91)<=6,"Q2",IF(MONTH(B91)<=9,"Q3","Q4"))) -> Q2 | Z91: =M91-O91 -> 119.98
A92: #ORD-10091 | B92: 2024-03-13 | C92: 13:15:45 | D92: Jack Sanchez | E92: jack.sanchez57@yahoo.com | F92: +1-500-428-2680 | G92: Portland | H92: OR | I92: United States | J92: Stainless Steel Cookware Set x3 | Insulated Water Bottle 32oz x1 | K92: Kitchen | L92: 2 | M92: 417.96 | N92: None | O92: 0 | P92: 0 | Q92: 41.8 | R92: 459.76 | S92: Debit Card | T92: Instagram | U92: Fulfilled | V92: 2024-03-18 | W92: 0 | X92: =TEXT(B92,"MMMM") -> March | Y92: =IF(MONTH(B92)<=3,"Q1",IF(MONTH(B92)<=6,"Q2",IF(MONTH(B92)<=9,"Q3","Q4"))) -> Q1 | Z92: =M92-O92 -> 417.96
A93: #ORD-10092 | B93: 2024-08-22 | C93: 00:50:26 | D93: Ethan Lee | E93: ethan.lee38@gmail.com | F93: +1-887-752-7655 | G93: El Paso | H93: TX | I93: United States | J93: Running Shoes - Men's x1 | Sunscreen SPF 50 Face x1 | K93: Footwear | L93: 2 | M93: 93.98 | N93: SAVE10 | O93: 9.4 | P93: 0 | Q93: 7.61 | R93: 92.19 | S93: Afterpay | T93: Online Store | U93: Fulfilled | V93: 2024-08-23 | W93: 0 | X93: =TEXT(B93,"MMMM") -> August | Y93: =IF(MONTH(B93)<=3,"Q1",IF(MONTH(B93)<=6,"Q2",IF(MONTH(B93)<=9,"Q3","Q4"))) -> Q3 | Z93: =M93-O93 -> 84.58
A94: #ORD-10093 | B94: 2024-02-25 | C94: 10:48:03 | D94: Alexander King | E94: alexander.king96@outlook.com | F94: +1-579-480-8273 | G94: Louisville | H94: KY | I94: United States | J94: Anti-Aging Serum 1oz x1 | High-Waist Leggings x1 | Organic Green Tea 100ct x2 | K94: Beauty | L94: 3 | M94: 122.96 | N94: SAVE10 | O94: 12.3 | P94: 0 | Q94: 8.85 | R94: 119.51 | S94: Debit Card | T94: Facebook | U94: Fulfilled | V94: 2024-02-29 | W94: 0 | X94: =TEXT(B94,"MMMM") -> February | Y94: =IF(MONTH(B94)<=3,"Q1",IF(MONTH(B94)<=6,"Q2",IF(MONTH(B94)<=9,"Q3","Q4"))) -> Q1 | Z94: =M94-O94 -> 110.66
A95: #ORD-10094 | B95: 2024-05-02 | C95: 02:17:04 | D95: Ava Nguyen | E95: ava.nguyen68@gmail.com | F95: +1-419-726-5678 | G95: Phoenix | H95: AZ | I95: United States | J95: Casual Sneakers x1 | Smart LED Desk Lamp x1 | K95: Footwear | L95: 2 | M95: 99.98 | N95: FLASH25 | O95: 25 | P95: 0 | Q95: 6.37 | R95: 81.35 | S95: Google Pay | T95: Online Store | U95: Fulfilled | V95: 2024-05-06 | W95: 0 | X95: =TEXT(B95,"MMMM") -> May | Y95: =IF(MONTH(B95)<=3,"Q1",IF(MONTH(B95)<=6,"Q2",IF(MONTH(B95)<=9,"Q3","Q4"))) -> Q2 | Z95: =M95-O95 -> 74.98
A96: #ORD-10095 | B96: 2024-12-15 | C96: 00:17:44 | D96: Michael Gonzalez | E96: michael.gonzalez18@yahoo.com | F96: +1-507-971-3580 | G96: Houston | H96: TX | I96: United States | J96: USB-C Fast Charger 65W x1 | High-Waist Leggings x2 | K96: Electronics | L96: 2 | M96: 115.97 | N96: SAVE10 | O96: 11.6 | P96: 0 | Q96: 10.44 | R96: 114.81 | S96: Credit Card | T96: Online Store | U96: Refunded | V96: 2024-12-18 | W96: 114.81 | X96: =TEXT(B96,"MMMM") -> December | Y96: =IF(MONTH(B96)<=3,"Q1",IF(MONTH(B96)<=6,"Q2",IF(MONTH(B96)<=9,"Q3","Q4"))) -> Q4 | Z96: =M96-O96 -> 104.37
A97: #ORD-10096 | B97: 2024-03-19 | C97: 01:16:22 | D97: Logan White | E97: logan.white29@gmail.com | F97: +1-934-836-8842 | G97: San Francisco | H97: CA | I97: United States | J97: Casual Sneakers x1 | High-Waist Leggings x1 | Stainless Steel Cookware Set x1 | K97: Footwear | L97: 3 | M97: 232.97 | N97: FLASH25 | O97: 58.24 | P97: 0 | Q97: 12.23 | R97: 186.96 | S97: PayPal | T97: Online Store | U97: Fulfilled | V97: 2024-03-23 | W97: 0 | X97: =TEXT(B97,"MMMM") -> March | Y97: =IF(MONTH(B97)<=3,"Q1",IF(MONTH(B97)<=6,"Q2",IF(MONTH(B97)<=9,"Q3","Q4"))) -> Q1 | Z97: =M97-O97 -> 174.73
A98: #ORD-10097 | B98: 2024-05-03 | C98: 02:54:43 | D98: Owen Clark | E98: owen.clark53@yahoo.com | F98: +1-730-256-5982 | G98: Memphis | H98: TN | I98: United States | J98: Organic Green Tea 100ct x1 | Anti-Aging Serum 1oz x1 | K98: Food & Beverage | L98: 2 | M98: 64.98 | N98: FLASH25 | O98: 16.25 | P98: 5.99 | Q98: 3.41 | R98: 58.13 | S98: Debit Card | T98: Direct | U98: Fulfilled | V98: 2024-05-04 | W98: 0 | X98: =TEXT(B98,"MMMM") -> May | Y98: =IF(MONTH(B98)<=3,"Q1",IF(MONTH(B98)<=6,"Q2",IF(MONTH(B98)<=9,"Q3","Q4"))) -> Q2 | Z98: =M98-O98 -> 48.73
A99: #ORD-10098 | B99: 2024-12-31 | C99: 09:51:41 | D99: Mia Hernandez | E99: mia.hernandez91@gmail.com | F99: +1-714-756-3762 | G99: Austin | H99: TX | I99: United States | J99: Yoga Mat Premium x1 | Canvas Backpack 25L x1 | K99: Sports & Fitness | L99: 2 | M99: 89.98 | N99: FLASH25 | O99: 22.5 | P99: 0 | Q99: 5.4 | R99: 72.88 | S99: Credit Card | T99: Online Store | U99: Refunded | V99: 2025-01-01 | W99: 72.88 | X99: =TEXT(B99,"MMMM") -> December | Y99: =IF(MONTH(B99)<=3,"Q1",IF(MONTH(B99)<=6,"Q2",IF(MONTH(B99)<=9,"Q3","Q4"))) -> Q4 | Z99: =M99-O99 -> 67.48
A100: #ORD-10099 | B100: 2024-08-23 | C100: 00:18:12 | D100: Daniel Hill | E100: daniel.hill22@outlook.com | F100: +1-985-685-7825 | G100: Phoenix | H100: AZ | I100: United States | J100: Bamboo Sunglasses x1 | K100: Bags & Accessories | L100: 1 | M100: 24.99 | N100: None | O100: 0 | P100: 4.99 | Q100: 1.5 | R100: 31.48 | S100: Google Pay | T100: Email Campaign | U100: Fulfilled | V100: 2024-08-25 | W100: 0 | X100: =TEXT(B100,"MMMM") -> August | Y100: =IF(MONTH(B100)<=3,"Q1",IF(MONTH(B100)<=6,"Q2",IF(MONTH(B100)<=9,"Q3","Q4"))) -> Q3 | Z100: =M100-O100 -> 24.99
...

Sheet KPIs
B2: SHOPIFY STORE — KPI SUMMARY 2024 | H2: Month Number | I2: Monthly Revenue
B3: Total Orders | D3: =COUNTA('Raw Data'!A2:A1001) -> 1000 | H3: 1 | I3: {=SUMPRODUCT((MONTH(Orders_Clean!B2:B1001)=1)*Orders_Clean!R2:R1001)} -> 12015.35
B4: Total Revenue | D4: =SUM('Raw Data'!R2:R1001) -> 137929.05 | H4: 2 | I4: {=SUMPRODUCT((MONTH(Orders_Clean!B2:B1001)=2)*Orders_Clean!R2:R1001)} -> 11262.67
B5: Average Order Value | D5: =AVERAGE('Raw Data'!R2:R1001) -> 137.92905 | H5: 3 | I5: {=SUMPRODUCT((MONTH(Orders_Clean!B2:B1001)=3)*Orders_Clean!R2:R1001)} -> 11094.63
B6: Total Discounts Given | D6: =SUM('Raw Data'!O2:O1001) -> 11873.42 | H6: 4 | I6: {=SUMPRODUCT((MONTH(Orders_Clean!B2:B1001)=4)*Orders_Clean!R2:R1001)} -> 10162.84
B7: Total Refunds | D7: =SUM('Raw Data'!W2:W1001) -> 13886.31 | H7: 5 | I7: {=SUMPRODUCT((MONTH(Orders_Clean!B2:B1001)=5)*Orders_Clean!R2:R1001)} -> 11951.2
B8: Refund Rate | D8: =COUNTIF('Raw Data'!U2:U1001,"Refunded")/COUNTA('Raw Data'!A2:A1001) -> 0.1 | H8: 6 | I8: {=SUMPRODUCT((MONTH(Orders_Clean!B2:B1001)=6)*Orders_Clean!R2:R1001)} -> 9587.24
B9: Cancellation Rate | D9: =COUNTIF('Raw Data'!U2:U1001,"Cancelled")/COUNTA('Raw Data'!A2:A1001) -> 0.117 | H9: 7 | I9: {=SUMPRODUCT((MONTH(Orders_Clean!B2:B1001)=7)*Orders_Clean!R2:R1001)} -> 10833.23
B10: Best Revenue Month | D10: =TEXT(DATE(2024,MATCH(MAX(I2:I13),I2:I13,0),1),"MMMM") -> November | H10: 8 | I10: {=SUMPRODUCT((MONTH(Orders_Clean!B2:B1001)=8)*Orders_Clean!R2:R1001)} -> 11882.41
B11: Free Shipping Orders | D11: =COUNTIF('Raw Data'!P2:P1001,0) -> 637 | H11: 9 | I11: {=SUMPRODUCT((MONTH(Orders_Clean!B2:B1001)=9)*Orders_Clean!R2:R1001)} -> 11557.71
H12: 10 | I12: {=SUMPRODUCT((MONTH(Orders_Clean!B2:B1001)=10)*Orders_Clean!R2:R1001)} -> 15430.39
H13: 11 | I13: {=SUMPRODUCT((MONTH(Orders_Clean!B2:B1001)=11)*Orders_Clean!R2:R1001)} -> 12119.81
H14: 12 | I14: {=SUMPRODUCT((MONTH(Orders_Clean!B2:B1001)=12)*Orders_Clean!R2:R1001)} -> 10031.57

Sheet Revenue by Month
A3: Months | B3: Sum of Revenue ($)
A4: January | B4: 12015.35
A5: February | B5: 11262.67
A6: March | B6: 11094.63
A7: April | B7: 10162.84
A8: May | B8: 11951.2
A9: June | B9: 9587.24
A10: July | B10: 10833.23
A11: August | B11: 11882.41
A12: September | B12: 11557.71
A13: October | B13: 15430.39
A14: November | B14: 12119.81
A15: December | B15: 10031.57
A16: (blank)
A17: Grand Total | B17: 137929.05

Sheet Orders by Sales
A3: Sales Channel | B3: Count of Orders | C3: Sum of Total Orders
A4: Direct | B4: 62 | C4: 8795.36
A5: Email Campaign | B5: 70 | C5: 9891.8
A6: Facebook | B6: 159 | C6: 22135.54
A7: Google Shopping | B7: 91 | C7: 13660.34
A8: Instagram | B8: 141 | C8: 18093.53
A9: Online Store | B9: 397 | C9: 54025.51
A10: Referral | B10: 32 | C10: 4946.67
A11: TikTok Shop | B11: 48 | C11: 6380.3
A12: (blank)
A13: Grand Total | B13: 1000 | C13: 137929.05

Sheet Fulfillment status breakdown
A3: Fulfillment Status | B3: Count of Orders | C3: % of Orders
A4: Cancelled | B4: 117 | C4: =B4/$B$9 -> 0.117
A5: Fulfilled | B5: 560 | C5: =B5/$B$9 -> 0.56
A6: Partially Fulfilled | B6: 115 | C6: =B6/$B$9 -> 0.115
A7: Refunded | B7: 100 | C7: =B7/$B$9 -> 0.1
A8: Unfulfilled | B8: 108 | C8: =B8/$B$9 -> 0.108
A9: Grand Total | B9: 1000 | C9: =B9/$B$9 -> 1

Sheet Revenue by Product
A3: Primary Category | B3: Sum Total of Orders
A4: Electronics | B4: 29497.7
A5: Footwear | B5: 20735.62
A6: Kitchen | B6: 18619.95
A7: Bags & Accessories | B7: 13417.3
A8: Beauty | B8: 12370.7
A9: Apparel | B9: 12082
A10: Home & Living | B10: 10360.24
A11: Sports & Fitness | B11: 10277.13
A12: Health & Nutrition | B12: 7646.82
A13: Food & Beverage | B13: 2921.59
A14: Grand Total | B14: 137929.05

Sheet Payment Method analysis
A3: Payment Method | B3: Average Total of Orders
A4: Afterpay | B4: 140.64429
A5: Apple Pay | B5: 139.37583
A6: Credit Card | B6: 135.61138
A7: Debit Card | B7: 133.9624
A8: Google Pay | B8: 128.45033
A9: Klarna | B9: 147.79774
A10: PayPal | B10: 150.2501
A11: Shop Pay | B11: 128.61853
A12: Grand Total | B12: 137.92905

Sheet Dashboard
A1: SHOPIFY STORE - EXECUTIVE SALES DASHBOARD - FY2024
B3: TOTAL REVENUE | F3: TOTAL ORDERS | J3: AVG ORDER VALUE | N3: REFUND RATE
B5: =SUM('Raw Data'!R2:R1001) -> 137929.05 | F5: =COUNTA('Raw Data'!A2:A1001) -> 1000 | J5: =AVERAGE('Raw Data'!R2:R1001) -> 137.92905 | N5: =COUNTIF('Raw Data'!U2:U1001,"Refunded")/COUNTA('Raw Data'!A2:A1001) -> 0.1

Sheet Insights
A1: SHOPIFY STORE - 2024 PERFORMANCE INSIGHTS
A3: EXECUTIVE SUMMARY
A5: The store prcessed 1,000 orders in 2024 generating $137929.05 in total revenue with an average order value of $137.9. The strongest sales channel was Online Store and peak revenue occurred in Q4 2024.Key areas for improvement include the refund rate and cancellation rate which together account for 11.70% of all orders processed during the year.
A7: # | B7: FINDING | C7: SUPPORTING DATA | D7: TREND
A8: 1 | B8: Q4 was the strongest quarter driving the highest revenue of the year | C8: {=SUMPRODUCT((Orders_Clean!Y2:Y1001="Q4")*Orders_Clean!R2:R1001)} -> 37581.77
A9: 2 | B9: Online Store is the top sales channel by both order volume and revenue | C9: =COUNTIF(Orders_Clean!T2:T1001,"Online Store") -> 397
A10: 3 | B10: More than half of all orders qualified for free shipping (order above $75) | C10: =COUNTIF(Orders_Clean!P2:P1001,0) -> 637
A11: 4 | B11: Discount codes were used in a significant portion of all orders | C11: =COUNTIF(Orders_Clean!N2:N1001,"<>None")/COUNTA(Orders_Clean!A2:A1001) -> 0.623
A12: 5 | B12: Refunded orders have the highest average order value among all statuses | C12: =AVERAGEIF(Orders_Clean!U2:U1001,"Refunded",Orders_Clean!R2:R1001) -> 138.8631
A13: 6 | B13: Electronics and Kitchen are the top two revenue generating categories | C13: =SUMIF(Orders_Clean!K2:K1001,"Electronics",Orders_Clean!R2:R1001) -> 29497.7
A14: 7 | B14: Shop Pay users show above average order values compared to other methods | C14: =AVERAGEIF(Orders_Clean!S2:S1001,"Shop Pay",Orders_Clean!R2:R1001) -> 128.61853
